{
"meta":{"test_sets":[],"test_metrics":[],"learn_metrics":[{"best_value":"Min","name":"RMSE"}],"launch_mode":"Train","parameters":"","iteration_count":1000,"learn_sets":["learn"],"name":"experiment"},
"iterations":[
{"learn":[14.59871775],"iteration":0,"passed_time":0.1620671668,"remaining_time":161.9050997},
{"learn":[14.22518863],"iteration":1,"passed_time":0.163883509,"remaining_time":81.77787101},
{"learn":[13.8866124],"iteration":2,"passed_time":0.1645201557,"remaining_time":54.67553174},
{"learn":[13.52356875],"iteration":3,"passed_time":0.1651349818,"remaining_time":41.11861047},
{"learn":[13.18870211],"iteration":4,"passed_time":0.1668569196,"remaining_time":33.204527},
{"learn":[12.9124226],"iteration":5,"passed_time":0.1677382406,"remaining_time":27.7886352},
{"learn":[12.60003351],"iteration":6,"passed_time":0.1686776246,"remaining_time":23.92812589},
{"learn":[12.32990573],"iteration":7,"passed_time":0.1707054516,"remaining_time":21.16747599},
{"learn":[12.0660619],"iteration":8,"passed_time":0.1720813917,"remaining_time":18.94807324},
{"learn":[11.77309809],"iteration":9,"passed_time":0.1732721109,"remaining_time":17.15393898},
{"learn":[11.49227636],"iteration":10,"passed_time":0.1741763676,"remaining_time":15.66003887},
{"learn":[11.26264833],"iteration":11,"passed_time":0.1751311951,"remaining_time":14.41913506},
{"learn":[11.04260393],"iteration":12,"passed_time":0.1760280421,"remaining_time":13.36459058},
{"learn":[10.79916926],"iteration":13,"passed_time":0.176864528,"remaining_time":12.45631605},
{"learn":[10.5541002],"iteration":14,"passed_time":0.1777742516,"remaining_time":11.67384252},
{"learn":[10.31918115],"iteration":15,"passed_time":0.1786652166,"remaining_time":10.98791082},
{"learn":[10.10004441],"iteration":16,"passed_time":0.1795926231,"remaining_time":10.38467932},
{"learn":[9.894556723],"iteration":17,"passed_time":0.1804693998,"remaining_time":9.845608369},
{"learn":[9.690174082],"iteration":18,"passed_time":0.1813373444,"remaining_time":9.362733412},
{"learn":[9.506034866],"iteration":19,"passed_time":0.1821605311,"remaining_time":8.925866023},
{"learn":[9.338524633],"iteration":20,"passed_time":0.182972842,"remaining_time":8.530019633},
{"learn":[9.170203312],"iteration":21,"passed_time":0.1838416781,"remaining_time":8.172598234},
{"learn":[9.010299969],"iteration":22,"passed_time":0.1846023794,"remaining_time":7.841588031},
{"learn":[8.843866678],"iteration":23,"passed_time":0.1854522377,"remaining_time":7.541724332},
{"learn":[8.690548059],"iteration":24,"passed_time":0.186261416,"remaining_time":7.264195223},
{"learn":[8.555307687],"iteration":25,"passed_time":0.1870761645,"remaining_time":7.008160933},
{"learn":[8.413851302],"iteration":26,"passed_time":0.1891499518,"remaining_time":6.816403819},
{"learn":[8.29256019],"iteration":27,"passed_time":0.1903042749,"remaining_time":6.606276973},
{"learn":[8.162193833],"iteration":28,"passed_time":0.191190941,"remaining_time":6.401600129},
{"learn":[8.040736294],"iteration":29,"passed_time":0.1920164654,"remaining_time":6.208532382},
{"learn":[7.921220278],"iteration":30,"passed_time":0.1926940853,"remaining_time":6.023244149},
{"learn":[7.809589039],"iteration":31,"passed_time":0.1933193864,"remaining_time":5.847911438},
{"learn":[7.699675801],"iteration":32,"passed_time":0.1939358813,"remaining_time":5.682909006},
{"learn":[7.60645267],"iteration":33,"passed_time":0.1945633823,"remaining_time":5.527889037},
{"learn":[7.498880302],"iteration":34,"passed_time":0.1951444113,"remaining_time":5.380410196},
{"learn":[7.401158744],"iteration":35,"passed_time":0.1958056337,"remaining_time":5.243239748},
{"learn":[7.306431077],"iteration":36,"passed_time":0.1964035995,"remaining_time":5.111801793},
{"learn":[7.223863468],"iteration":37,"passed_time":0.1970693117,"remaining_time":4.988965206},
{"learn":[7.143477682],"iteration":38,"passed_time":0.1976967345,"remaining_time":4.871450304},
{"learn":[7.062817131],"iteration":39,"passed_time":0.198302525,"remaining_time":4.7592606},
{"learn":[6.990793435],"iteration":40,"passed_time":0.1989179956,"remaining_time":4.652740434},
{"learn":[6.931862224],"iteration":41,"passed_time":0.1997461946,"remaining_time":4.556115583},
{"learn":[6.858296558],"iteration":42,"passed_time":0.2004641028,"remaining_time":4.461491776},
{"learn":[6.786268161],"iteration":43,"passed_time":0.2010838068,"remaining_time":4.369002711},
{"learn":[6.717118549],"iteration":44,"passed_time":0.2017846891,"remaining_time":4.282319512},
{"learn":[6.652948106],"iteration":45,"passed_time":0.2025896937,"remaining_time":4.201534082},
{"learn":[6.589686076],"iteration":46,"passed_time":0.2032392429,"remaining_time":4.120999968},
{"learn":[6.531283097],"iteration":47,"passed_time":0.2038739628,"remaining_time":4.043500262},
{"learn":[6.471368031],"iteration":48,"passed_time":0.2045111313,"remaining_time":3.969185425},
{"learn":[6.416481395],"iteration":49,"passed_time":0.2051766922,"remaining_time":3.898357151},
{"learn":[6.369870822],"iteration":50,"passed_time":0.2058121338,"remaining_time":3.829719902},
{"learn":[6.325678067],"iteration":51,"passed_time":0.2064015556,"remaining_time":3.762859129},
{"learn":[6.275766122],"iteration":52,"passed_time":0.2070895908,"remaining_time":3.700261178},
{"learn":[6.224773967],"iteration":53,"passed_time":0.2076744884,"remaining_time":3.638149371},
{"learn":[6.182249254],"iteration":54,"passed_time":0.2082880759,"remaining_time":3.57876785},
{"learn":[6.139904173],"iteration":55,"passed_time":0.2092970305,"remaining_time":3.528149943},
{"learn":[6.100525536],"iteration":56,"passed_time":0.210518926,"remaining_time":3.482795566},
{"learn":[6.062568564],"iteration":57,"passed_time":0.2120530314,"remaining_time":3.444033717},
{"learn":[6.030559288],"iteration":58,"passed_time":0.213139546,"remaining_time":3.399395132},
{"learn":[5.997931376],"iteration":59,"passed_time":0.2139747539,"remaining_time":3.352271144},
{"learn":[5.964103835],"iteration":60,"passed_time":0.2149473661,"remaining_time":3.308779946},
{"learn":[5.933729724],"iteration":61,"passed_time":0.2157705486,"remaining_time":3.26439959},
{"learn":[5.901932711],"iteration":62,"passed_time":0.2164849838,"remaining_time":3.219784601},
{"learn":[5.873727795],"iteration":63,"passed_time":0.217244534,"remaining_time":3.17720131},
{"learn":[5.846485734],"iteration":64,"passed_time":0.2178667874,"remaining_time":3.133929942},
{"learn":[5.820630862],"iteration":65,"passed_time":0.2184778012,"remaining_time":3.091791914},
{"learn":[5.793646238],"iteration":66,"passed_time":0.2190664717,"remaining_time":3.05058236},
{"learn":[5.765388646],"iteration":67,"passed_time":0.2197007857,"remaining_time":3.011193122},
{"learn":[5.747073912],"iteration":68,"passed_time":0.2202836776,"remaining_time":2.972233389},
{"learn":[5.722315217],"iteration":69,"passed_time":0.2208811476,"remaining_time":2.934563819},
{"learn":[5.699970599],"iteration":70,"passed_time":0.2217739008,"remaining_time":2.901802166},
{"learn":[5.682732647],"iteration":71,"passed_time":0.2226768617,"remaining_time":2.870057328},
{"learn":[5.663525791],"iteration":72,"passed_time":0.223669476,"remaining_time":2.840295949},
{"learn":[5.642381613],"iteration":73,"passed_time":0.2254522791,"remaining_time":2.821200141},
{"learn":[5.621404779],"iteration":74,"passed_time":0.2264268844,"remaining_time":2.792598242},
{"learn":[5.602460129],"iteration":75,"passed_time":0.2270805528,"remaining_time":2.760821457},
{"learn":[5.587337574],"iteration":76,"passed_time":0.2276670344,"remaining_time":2.729047698},
{"learn":[5.572393026],"iteration":77,"passed_time":0.2283478179,"remaining_time":2.699188309},
{"learn":[5.558425806],"iteration":78,"passed_time":0.2290501942,"remaining_time":2.670319352},
{"learn":[5.541518902],"iteration":79,"passed_time":0.2296514455,"remaining_time":2.640991623},
{"learn":[5.526157283],"iteration":80,"passed_time":0.2302511439,"remaining_time":2.612355571},
{"learn":[5.511746977],"iteration":81,"passed_time":0.2308655255,"remaining_time":2.584567713},
{"learn":[5.504975022],"iteration":82,"passed_time":0.2311859374,"remaining_time":2.554186802},
{"learn":[5.493980522],"iteration":83,"passed_time":0.2318286912,"remaining_time":2.528036681},
{"learn":[5.480745463],"iteration":84,"passed_time":0.2324351498,"remaining_time":2.502096024},
{"learn":[5.464052013],"iteration":85,"passed_time":0.2330663018,"remaining_time":2.477006975},
{"learn":[5.449143727],"iteration":86,"passed_time":0.2336710226,"remaining_time":2.452202801},
{"learn":[5.438255432],"iteration":87,"passed_time":0.2347392098,"remaining_time":2.43275181},
{"learn":[5.425927931],"iteration":88,"passed_time":0.235384366,"remaining_time":2.409383791},
{"learn":[5.412331217],"iteration":89,"passed_time":0.2359954352,"remaining_time":2.386176067},
{"learn":[5.400691499],"iteration":90,"passed_time":0.236579506,"remaining_time":2.363195285},
{"learn":[5.391618744],"iteration":91,"passed_time":0.2372365204,"remaining_time":2.34142131},
{"learn":[5.380766572],"iteration":92,"passed_time":0.2382316052,"remaining_time":2.323398558},
{"learn":[5.372207183],"iteration":93,"passed_time":0.2396119383,"remaining_time":2.309451235},
{"learn":[5.362918837],"iteration":94,"passed_time":0.2407811916,"remaining_time":2.293757667},
{"learn":[5.348292324],"iteration":95,"passed_time":0.2415192397,"remaining_time":2.274306174},
{"learn":[5.339772295],"iteration":96,"passed_time":0.2421391521,"remaining_time":2.254140766},
{"learn":[5.331515983],"iteration":97,"passed_time":0.2427479659,"remaining_time":2.234272095},
{"learn":[5.323861644],"iteration":98,"passed_time":0.2433400119,"remaining_time":2.214639906},
{"learn":[5.313277281],"iteration":99,"passed_time":0.2439529062,"remaining_time":2.195576156},
{"learn":[5.30685627],"iteration":100,"passed_time":0.2445552272,"remaining_time":2.176783656},
{"learn":[5.29652059],"iteration":101,"passed_time":0.245166972,"remaining_time":2.158430792},
{"learn":[5.288350766],"iteration":102,"passed_time":0.245781225,"remaining_time":2.140444261},
{"learn":[5.27993346],"iteration":103,"passed_time":0.2464495933,"remaining_time":2.123258035},
{"learn":[5.271789139],"iteration":104,"passed_time":0.2471982173,"remaining_time":2.107070519},
{"learn":[5.262684686],"iteration":105,"passed_time":0.247952498,"remaining_time":2.091222012},
{"learn":[5.251619772],"iteration":106,"passed_time":0.2485989542,"remaining_time":2.074755758},
{"learn":[5.241012171],"iteration":107,"passed_time":0.2492093847,"remaining_time":2.058284918},
{"learn":[5.232684032],"iteration":108,"passed_time":0.2498593264,"remaining_time":2.042428072},
{"learn":[5.224267141],"iteration":109,"passed_time":0.2504742265,"remaining_time":2.026564196},
{"learn":[5.216324968],"iteration":110,"passed_time":0.2511351238,"remaining_time":2.011343469},
{"learn":[5.211102527],"iteration":111,"passed_time":0.2517486735,"remaining_time":1.99600734},
{"learn":[5.206364257],"iteration":112,"passed_time":0.2539513681,"remaining_time":1.993405872},
{"learn":[5.196937641],"iteration":113,"passed_time":0.2552684664,"remaining_time":1.983928607},
{"learn":[5.190746047],"iteration":114,"passed_time":0.2563622427,"remaining_time":1.97287465},
{"learn":[5.181885213],"iteration":115,"passed_time":0.2571042872,"remaining_time":1.959311982},
{"learn":[5.178293568],"iteration":116,"passed_time":0.2575913714,"remaining_time":1.944044282},
{"learn":[5.170991438],"iteration":117,"passed_time":0.2582332741,"remaining_time":1.930184303},
{"learn":[5.166257212],"iteration":118,"passed_time":0.2589224924,"remaining_time":1.916896771},
{"learn":[5.161421246],"iteration":119,"passed_time":0.2597795762,"remaining_time":1.905050226},
{"learn":[5.158223542],"iteration":120,"passed_time":0.2606604527,"remaining_time":1.893558165},
{"learn":[5.15470988],"iteration":121,"passed_time":0.2614543311,"remaining_time":1.881613957},
{"learn":[5.146388143],"iteration":122,"passed_time":0.262113026,"remaining_time":1.868887186},
{"learn":[5.139529364],"iteration":123,"passed_time":0.2627334006,"remaining_time":1.856084346},
{"learn":[5.134276023],"iteration":124,"passed_time":0.2633172521,"remaining_time":1.843220764},
{"learn":[5.128536065],"iteration":125,"passed_time":0.2639736353,"remaining_time":1.831055217},
{"learn":[5.123300353],"iteration":126,"passed_time":0.2644548241,"remaining_time":1.817866626},
{"learn":[5.116200518],"iteration":127,"passed_time":0.2651085899,"remaining_time":1.806052269},
{"learn":[5.108728704],"iteration":128,"passed_time":0.2660769494,"remaining_time":1.796535061},
{"learn":[5.104075866],"iteration":129,"passed_time":0.2672643327,"remaining_time":1.78861515},
{"learn":[5.100317606],"iteration":130,"passed_time":0.2687514183,"remaining_time":1.782786126},
{"learn":[5.095814182],"iteration":131,"passed_time":0.2697881888,"remaining_time":1.774061726},
{"learn":[5.092146915],"iteration":132,"passed_time":0.2706016778,"remaining_time":1.763997403},
{"learn":[5.085258329],"iteration":133,"passed_time":0.2713810923,"remaining_time":1.75385094},
{"learn":[5.079219421],"iteration":134,"passed_time":0.2727698921,"remaining_time":1.747747827},
{"learn":[5.076476829],"iteration":135,"passed_time":0.273563884,"remaining_time":1.737935263},
{"learn":[5.072133867],"iteration":136,"passed_time":0.2742621891,"remaining_time":1.7276516},
{"learn":[5.067031564],"iteration":137,"passed_time":0.2754437098,"remaining_time":1.720525201},
{"learn":[5.061358312],"iteration":138,"passed_time":0.2762972157,"remaining_time":1.711452537},
{"learn":[5.056759124],"iteration":139,"passed_time":0.2769602111,"remaining_time":1.701327011},
{"learn":[5.050254],"iteration":140,"passed_time":0.2777151919,"remaining_time":1.691896098},
{"learn":[5.048376474],"iteration":141,"passed_time":0.2782855559,"remaining_time":1.68147188},
{"learn":[5.042603751],"iteration":142,"passed_time":0.2791203915,"remaining_time":1.672770458},
{"learn":[5.037477349],"iteration":143,"passed_time":0.279816617,"remaining_time":1.663354334},
{"learn":[5.03230489],"iteration":144,"passed_time":0.2804380545,"remaining_time":1.653617493},
{"learn":[5.025976187],"iteration":145,"passed_time":0.2810490371,"remaining_time":1.643944368},
{"learn":[5.01952451],"iteration":146,"passed_time":0.2827170546,"remaining_time":1.640528215},
{"learn":[5.017569424],"iteration":147,"passed_time":0.2840556583,"remaining_time":1.63523933},
{"learn":[5.008962367],"iteration":148,"passed_time":0.2853328312,"remaining_time":1.629652613},
{"learn":[5.003880266],"iteration":149,"passed_time":0.2862188973,"remaining_time":1.621907085},
{"learn":[4.996387564],"iteration":150,"passed_time":0.287163654,"remaining_time":1.614582399},
{"learn":[4.993361683],"iteration":151,"passed_time":0.2879479347,"remaining_time":1.606446372},
{"learn":[4.99005752],"iteration":152,"passed_time":0.2886167164,"remaining_time":1.597767051},
{"learn":[4.986908764],"iteration":153,"passed_time":0.2892347238,"remaining_time":1.588912833},
{"learn":[4.985207175],"iteration":154,"passed_time":0.2899669883,"remaining_time":1.580787775},
{"learn":[4.979003494],"iteration":155,"passed_time":0.2908788873,"remaining_time":1.573729365},
{"learn":[4.973142217],"iteration":156,"passed_time":0.2915755051,"remaining_time":1.565593317},
{"learn":[4.967056696],"iteration":157,"passed_time":0.2922225713,"remaining_time":1.557287374},
{"learn":[4.961460696],"iteration":158,"passed_time":0.292849916,"remaining_time":1.548973455},
{"learn":[4.954240363],"iteration":159,"passed_time":0.2934481767,"remaining_time":1.540602928},
{"learn":[4.952320707],"iteration":160,"passed_time":0.2938610024,"remaining_time":1.531362615},
{"learn":[4.948337777],"iteration":161,"passed_time":0.2944610101,"remaining_time":1.523199546},
{"learn":[4.943228639],"iteration":162,"passed_time":0.2950702113,"remaining_time":1.515176484},
{"learn":[4.938545759],"iteration":163,"passed_time":0.2958297438,"remaining_time":1.508010158},
{"learn":[4.935330572],"iteration":164,"passed_time":0.2981848571,"remaining_time":1.508996095},
{"learn":[4.932051543],"iteration":165,"passed_time":0.2993130977,"remaining_time":1.503777853},
{"learn":[4.928964153],"iteration":166,"passed_time":0.3003022585,"remaining_time":1.497914858},
{"learn":[4.922860227],"iteration":167,"passed_time":0.3012364344,"remaining_time":1.49183758},
{"learn":[4.917668772],"iteration":168,"passed_time":0.3023928297,"remaining_time":1.486913855},
{"learn":[4.910365386],"iteration":169,"passed_time":0.3032934411,"remaining_time":1.480785624},
{"learn":[4.906457206],"iteration":170,"passed_time":0.3046720836,"remaining_time":1.477036008},
{"learn":[4.901996508],"iteration":171,"passed_time":0.3055292094,"remaining_time":1.470803404},
{"learn":[4.896816173],"iteration":172,"passed_time":0.306140524,"remaining_time":1.463457881},
{"learn":[4.891123132],"iteration":173,"passed_time":0.3067619842,"remaining_time":1.456237925},
{"learn":[4.887630202],"iteration":174,"passed_time":0.3074464515,"remaining_time":1.449390414},
{"learn":[4.885259712],"iteration":175,"passed_time":0.3083221115,"remaining_time":1.443508067},
{"learn":[4.880659728],"iteration":176,"passed_time":0.3091516827,"remaining_time":1.437467994},
{"learn":[4.877299723],"iteration":177,"passed_time":0.3101991047,"remaining_time":1.432492495},
{"learn":[4.874038772],"iteration":178,"passed_time":0.3116439961,"remaining_time":1.429383915},
{"learn":[4.86943698],"iteration":179,"passed_time":0.3128545604,"remaining_time":1.425226331},
{"learn":[4.861268711],"iteration":180,"passed_time":0.3140026705,"remaining_time":1.420818713},
{"learn":[4.858673056],"iteration":181,"passed_time":0.3154691152,"remaining_time":1.417877672},
{"learn":[4.854036207],"iteration":182,"passed_time":0.3163200935,"remaining_time":1.412205008},
{"learn":[4.85130244],"iteration":183,"passed_time":0.3170827645,"remaining_time":1.40619313},
{"learn":[4.847510084],"iteration":184,"passed_time":0.3177582879,"remaining_time":1.399854079},
{"learn":[4.845691673],"iteration":185,"passed_time":0.3183695864,"remaining_time":1.393294857},
{"learn":[4.842058646],"iteration":186,"passed_time":0.3190716342,"remaining_time":1.387193789},
{"learn":[4.838623675],"iteration":187,"passed_time":0.319966541,"remaining_time":1.381983145},
{"learn":[4.834602161],"iteration":188,"passed_time":0.3209086441,"remaining_time":1.37702069},
{"learn":[4.830858976],"iteration":189,"passed_time":0.3217519481,"remaining_time":1.371679358},
{"learn":[4.827590511],"iteration":190,"passed_time":0.3226322011,"remaining_time":1.366541627},
{"learn":[4.822246226],"iteration":191,"passed_time":0.3234526998,"remaining_time":1.361196778},
{"learn":[4.816686395],"iteration":192,"passed_time":0.3269209689,"remaining_time":1.366970061},
{"learn":[4.814797121],"iteration":193,"passed_time":0.3287406579,"remaining_time":1.365798816},
{"learn":[4.811639392],"iteration":194,"passed_time":0.3297123122,"remaining_time":1.361120058},
{"learn":[4.804813432],"iteration":195,"passed_time":0.3305896999,"remaining_time":1.356092442},
{"learn":[4.80251613],"iteration":196,"passed_time":0.3318381568,"remaining_time":1.352619492},
{"learn":[4.800087884],"iteration":197,"passed_time":0.3332581128,"remaining_time":1.349863669},
{"learn":[4.794773135],"iteration":198,"passed_time":0.3346484503,"remaining_time":1.347002054},
{"learn":[4.791664833],"iteration":199,"passed_time":0.3356014326,"remaining_time":1.34240573},
{"learn":[4.785989873],"iteration":200,"passed_time":0.3365604994,"remaining_time":1.337869846},
{"learn":[4.782387142],"iteration":201,"passed_time":0.3373783293,"remaining_time":1.33281142},
{"learn":[4.778623704],"iteration":202,"passed_time":0.338090268,"remaining_time":1.327379033},
{"learn":[4.775772178],"iteration":203,"passed_time":0.3403395389,"remaining_time":1.327991534},
{"learn":[4.77023101],"iteration":204,"passed_time":0.3417219189,"remaining_time":1.325214271},
{"learn":[4.764496689],"iteration":205,"passed_time":0.3431133152,"remaining_time":1.322485302},
{"learn":[4.763138716],"iteration":206,"passed_time":0.3443251374,"remaining_time":1.319081324},
{"learn":[4.758053283],"iteration":207,"passed_time":0.3452625156,"remaining_time":1.314653425},
{"learn":[4.755063788],"iteration":208,"passed_time":0.3460238766,"remaining_time":1.309592758},
{"learn":[4.752465267],"iteration":209,"passed_time":0.3467610609,"remaining_time":1.304482086},
{"learn":[4.748067377],"iteration":210,"passed_time":0.347429346,"remaining_time":1.299155232},
{"learn":[4.744163298],"iteration":211,"passed_time":0.3480892014,"remaining_time":1.293840994},
{"learn":[4.736670896],"iteration":212,"passed_time":0.3488169703,"remaining_time":1.288821388},
{"learn":[4.73349255],"iteration":213,"passed_time":0.3494306536,"remaining_time":1.283422868},
{"learn":[4.731864595],"iteration":214,"passed_time":0.3504689509,"remaining_time":1.279619193},
{"learn":[4.728398311],"iteration":215,"passed_time":0.3515290167,"remaining_time":1.275920135},
{"learn":[4.723865975],"iteration":216,"passed_time":0.3524690905,"remaining_time":1.271812433},
{"learn":[4.723483365],"iteration":217,"passed_time":0.3536793985,"remaining_time":1.268703164},
{"learn":[4.72095416],"iteration":218,"passed_time":0.3563791944,"remaining_time":1.270923063},
{"learn":[4.716173382],"iteration":219,"passed_time":0.3577470526,"remaining_time":1.268375914},
{"learn":[4.710563974],"iteration":220,"passed_time":0.3586507992,"remaining_time":1.264203496},
{"learn":[4.707160263],"iteration":221,"passed_time":0.3595578725,"remaining_time":1.260072184},
{"learn":[4.70408351],"iteration":222,"passed_time":0.3603495283,"remaining_time":1.255567639},
{"learn":[4.702501831],"iteration":223,"passed_time":0.3612648238,"remaining_time":1.251524568},
{"learn":[4.700269738],"iteration":224,"passed_time":0.3621999483,"remaining_time":1.2475776},
{"learn":[4.695346302],"iteration":225,"passed_time":0.3629902395,"remaining_time":1.243161263},
{"learn":[4.689769299],"iteration":226,"passed_time":0.3639333577,"remaining_time":1.239297293},
{"learn":[4.687919514],"iteration":227,"passed_time":0.3647709259,"remaining_time":1.235101556},
{"learn":[4.682982074],"iteration":228,"passed_time":0.3654778314,"remaining_time":1.230495231},
{"learn":[4.679578702],"iteration":229,"passed_time":0.3662179853,"remaining_time":1.226034125},
{"learn":[4.675751423],"iteration":230,"passed_time":0.3671431037,"remaining_time":1.222220981},
{"learn":[4.672710726],"iteration":231,"passed_time":0.3682748744,"remaining_time":1.219116826},
{"learn":[4.6690533],"iteration":232,"passed_time":0.3701979799,"remaining_time":1.218634552},
{"learn":[4.667595702],"iteration":233,"passed_time":0.3713956795,"remaining_time":1.215765344},
{"learn":[4.664241291],"iteration":234,"passed_time":0.3722377348,"remaining_time":1.211752626},
{"learn":[4.662246999],"iteration":235,"passed_time":0.3732622371,"remaining_time":1.208357412},
{"learn":[4.658668443],"iteration":236,"passed_time":0.3741421969,"remaining_time":1.204516862},
{"learn":[4.658017572],"iteration":237,"passed_time":0.3757781483,"remaining_time":1.203121634},
{"learn":[4.657656705],"iteration":238,"passed_time":0.3766366892,"remaining_time":1.19924904},
{"learn":[4.653242871],"iteration":239,"passed_time":0.3773797311,"remaining_time":1.195035815},
{"learn":[4.6507302],"iteration":240,"passed_time":0.3780555847,"remaining_time":1.190639787},
{"learn":[4.647671336],"iteration":241,"passed_time":0.3788841761,"remaining_time":1.186752915},
{"learn":[4.645506007],"iteration":242,"passed_time":0.380051953,"remaining_time":1.183947854},
{"learn":[4.641297906],"iteration":243,"passed_time":0.3839115272,"remaining_time":1.189496371},
{"learn":[4.63798107],"iteration":244,"passed_time":0.3857878675,"remaining_time":1.18885649},
{"learn":[4.635062318],"iteration":245,"passed_time":0.3869173963,"remaining_time":1.185917548},
{"learn":[4.631606017],"iteration":246,"passed_time":0.3888986093,"remaining_time":1.185589688},
{"learn":[4.630215494],"iteration":247,"passed_time":0.3916573328,"remaining_time":1.187606106},
{"learn":[4.62729814],"iteration":248,"passed_time":0.3927110468,"remaining_time":1.184441752},
{"learn":[4.624691756],"iteration":249,"passed_time":0.3936445042,"remaining_time":1.180933513},
{"learn":[4.621840053],"iteration":250,"passed_time":0.3945302553,"remaining_time":1.177303431},
{"learn":[4.619602091],"iteration":251,"passed_time":0.3953332457,"remaining_time":1.173449475},
{"learn":[4.613584029],"iteration":252,"passed_time":0.3962892051,"remaining_time":1.170071289},
{"learn":[4.6119388],"iteration":253,"passed_time":0.3988639942,"remaining_time":1.171466692},
{"learn":[4.60870702],"iteration":254,"passed_time":0.4005211788,"remaining_time":1.170150111},
{"learn":[4.604771557],"iteration":255,"passed_time":0.4013675044,"remaining_time":1.16647431},
{"learn":[4.604231277],"iteration":256,"passed_time":0.4022601097,"remaining_time":1.162954325},
{"learn":[4.600750354],"iteration":257,"passed_time":0.4033864572,"remaining_time":1.160126943},
{"learn":[4.596488253],"iteration":258,"passed_time":0.404304092,"remaining_time":1.156715568},
{"learn":[4.59470784],"iteration":259,"passed_time":0.4052291037,"remaining_time":1.153344372},
{"learn":[4.588818005],"iteration":260,"passed_time":0.4063862552,"remaining_time":1.150649205},
{"learn":[4.585054174],"iteration":261,"passed_time":0.4073442263,"remaining_time":1.147404729},
{"learn":[4.581471435],"iteration":262,"passed_time":0.4081955256,"remaining_time":1.143878716},
{"learn":[4.577555199],"iteration":263,"passed_time":0.4102940332,"remaining_time":1.143850032},
{"learn":[4.57457145],"iteration":264,"passed_time":0.414830676,"remaining_time":1.150568101},
{"learn":[4.573029224],"iteration":265,"passed_time":0.4168710955,"remaining_time":1.150313474},
{"learn":[4.571326203],"iteration":266,"passed_time":0.4181960202,"remaining_time":1.148081209},
{"learn":[4.571019224],"iteration":267,"passed_time":0.4197941335,"remaining_time":1.146601887},
{"learn":[4.565766631],"iteration":268,"passed_time":0.4209284629,"remaining_time":1.143861362},
{"learn":[4.563383471],"iteration":269,"passed_time":0.421611216,"remaining_time":1.139911806},
{"learn":[4.558165805],"iteration":270,"passed_time":0.4222994965,"remaining_time":1.136001229},
{"learn":[4.55629209],"iteration":271,"passed_time":0.4231195532,"remaining_time":1.132467039},
{"learn":[4.549383848],"iteration":272,"passed_time":0.423887013,"remaining_time":1.128812668},
{"learn":[4.546227503],"iteration":273,"passed_time":0.4246689475,"remaining_time":1.125217722},
{"learn":[4.540620977],"iteration":274,"passed_time":0.4253806771,"remaining_time":1.121458149},
{"learn":[4.532898237],"iteration":275,"passed_time":0.4285699411,"remaining_time":1.124219701},
{"learn":[4.529757367],"iteration":276,"passed_time":0.430078585,"remaining_time":1.122551686},
{"learn":[4.52579294],"iteration":277,"passed_time":0.4312103363,"remaining_time":1.119905981},
{"learn":[4.521572155],"iteration":278,"passed_time":0.432164011,"remaining_time":1.116810939},
{"learn":[4.518818099],"iteration":279,"passed_time":0.4331091173,"remaining_time":1.113709159},
{"learn":[4.514012334],"iteration":280,"passed_time":0.4341399529,"remaining_time":1.110842086},
{"learn":[4.508331416],"iteration":281,"passed_time":0.4349392318,"remaining_time":1.10739847},
{"learn":[4.506038537],"iteration":282,"passed_time":0.4357230049,"remaining_time":1.103934256},
{"learn":[4.505805643],"iteration":283,"passed_time":0.4368807304,"remaining_time":1.101431701},
{"learn":[4.501550352],"iteration":284,"passed_time":0.4377199892,"remaining_time":1.098139622},
{"learn":[4.494692643],"iteration":285,"passed_time":0.4384751909,"remaining_time":1.094654847},
{"learn":[4.489330245],"iteration":286,"passed_time":0.4391119586,"remaining_time":1.090894866},
{"learn":[4.484826955],"iteration":287,"passed_time":0.4399879052,"remaining_time":1.087747877},
{"learn":[4.478285428],"iteration":288,"passed_time":0.4430942741,"remaining_time":1.090103906},
{"learn":[4.475311671],"iteration":289,"passed_time":0.4445552797,"remaining_time":1.088393961},
{"learn":[4.471581298],"iteration":290,"passed_time":0.4454558769,"remaining_time":1.085320332},
{"learn":[4.469164956],"iteration":291,"passed_time":0.4463264263,"remaining_time":1.082188732},
{"learn":[4.462068024],"iteration":292,"passed_time":0.4472513397,"remaining_time":1.079203745},
{"learn":[4.458540976],"iteration":293,"passed_time":0.4487839401,"remaining_time":1.077692047},
{"learn":[4.455757458],"iteration":294,"passed_time":0.4504733454,"remaining_time":1.076554944},
{"learn":[4.453027414],"iteration":295,"passed_time":0.4512497013,"remaining_time":1.073242533},
{"learn":[4.450659338],"iteration":296,"passed_time":0.4519769484,"remaining_time":1.069830959},
{"learn":[4.444696901],"iteration":297,"passed_time":0.4526609729,"remaining_time":1.06633558},
{"learn":[4.442052813],"iteration":298,"passed_time":0.4533749292,"remaining_time":1.062929182},
{"learn":[4.440036756],"iteration":299,"passed_time":0.4541145587,"remaining_time":1.059600637},
{"learn":[4.435017051],"iteration":300,"passed_time":0.4568688152,"remaining_time":1.06096778},
{"learn":[4.429962125],"iteration":301,"passed_time":0.4584893944,"remaining_time":1.059687408},
{"learn":[4.427666256],"iteration":302,"passed_time":0.4596998722,"remaining_time":1.057461422},
{"learn":[4.425030004],"iteration":303,"passed_time":0.4606139854,"remaining_time":1.054563598},
{"learn":[4.422588771],"iteration":304,"passed_time":0.4618355448,"remaining_time":1.052379356},
{"learn":[4.418936667],"iteration":305,"passed_time":0.4637914543,"remaining_time":1.051866893},
{"learn":[4.416887976],"iteration":306,"passed_time":0.4647752742,"remaining_time":1.0491507},
{"learn":[4.413773354],"iteration":307,"passed_time":0.465545391,"remaining_time":1.045965619},
{"learn":[4.411129391],"iteration":308,"passed_time":0.4663121424,"remaining_time":1.042788642},
{"learn":[4.40850819],"iteration":309,"passed_time":0.4672556328,"remaining_time":1.040020602},
{"learn":[4.404880292],"iteration":310,"passed_time":0.4682764547,"remaining_time":1.037435618},
{"learn":[4.404593827],"iteration":311,"passed_time":0.4691745639,"remaining_time":1.034590064},
{"learn":[4.402139942],"iteration":312,"passed_time":0.4723992056,"remaining_time":1.036863432},
{"learn":[4.400284725],"iteration":313,"passed_time":0.4745763824,"remaining_time":1.03681337},
{"learn":[4.395805521],"iteration":314,"passed_time":0.4755017663,"remaining_time":1.034027651},
{"learn":[4.392838833],"iteration":315,"passed_time":0.4764889676,"remaining_time":1.031387512},
{"learn":[4.389213061],"iteration":316,"passed_time":0.4778590971,"remaining_time":1.02958285},
{"learn":[4.3861981],"iteration":317,"passed_time":0.4787587574,"remaining_time":1.026771926},
{"learn":[4.385054234],"iteration":318,"passed_time":0.4794322001,"remaining_time":1.023490057},
{"learn":[4.379364607],"iteration":319,"passed_time":0.4804285529,"remaining_time":1.020910675},
{"learn":[4.378387619],"iteration":320,"passed_time":0.481333733,"remaining_time":1.018148301},
{"learn":[4.375816727],"iteration":321,"passed_time":0.4820131637,"remaining_time":1.014922127},
{"learn":[4.374600202],"iteration":322,"passed_time":0.4827634379,"remaining_time":1.011860209},
{"learn":[4.37098897],"iteration":323,"passed_time":0.4834258847,"remaining_time":1.008629315},
{"learn":[4.367418484],"iteration":324,"passed_time":0.4841283963,"remaining_time":1.005497439},
{"learn":[4.363584638],"iteration":325,"passed_time":0.4870286533,"remaining_time":1.006924271},
{"learn":[4.360770706],"iteration":326,"passed_time":0.4880994352,"remaining_time":1.004559388},
{"learn":[4.358675808],"iteration":327,"passed_time":0.4891467186,"remaining_time":1.002154253},
{"learn":[4.354228195],"iteration":328,"passed_time":0.4901204492,"remaining_time":0.9996073599},
{"learn":[4.353773425],"iteration":329,"passed_time":0.4921221921,"remaining_time":0.9991571778},
{"learn":[4.351648009],"iteration":330,"passed_time":0.4932011374,"remaining_time":0.9968325103},
{"learn":[4.348209927],"iteration":331,"passed_time":0.4942613813,"remaining_time":0.994477719},
{"learn":[4.345852733],"iteration":332,"passed_time":0.4949912072,"remaining_time":0.9914688745},
{"learn":[4.34237339],"iteration":333,"passed_time":0.49566828,"remaining_time":0.9883684865},
{"learn":[4.340814362],"iteration":334,"passed_time":0.4963519062,"remaining_time":0.985295575},
{"learn":[4.339707068],"iteration":335,"passed_time":0.4971413949,"remaining_time":0.98244609},
{"learn":[4.335430786],"iteration":336,"passed_time":0.5003395903,"remaining_time":0.9843476213},
{"learn":[4.33521887],"iteration":337,"passed_time":0.5020156569,"remaining_time":0.9832377659},
{"learn":[4.328507238],"iteration":338,"passed_time":0.5035200288,"remaining_time":0.9817897906},
{"learn":[4.326140732],"iteration":339,"passed_time":0.5050001114,"remaining_time":0.9802943338},
{"learn":[4.323785636],"iteration":340,"passed_time":0.5066183739,"remaining_time":0.979066007},
{"learn":[4.320632534],"iteration":341,"passed_time":0.507623958,"remaining_time":0.976656621},
{"learn":[4.31973724],"iteration":342,"passed_time":0.5083339389,"remaining_time":0.9736892067},
{"learn":[4.318000924],"iteration":343,"passed_time":0.5090799916,"remaining_time":0.970803705},
{"learn":[4.312713628],"iteration":344,"passed_time":0.5101247071,"remaining_time":0.9684976322},
{"learn":[4.308220789],"iteration":345,"passed_time":0.5109949943,"remaining_time":0.9658691511},
{"learn":[4.305890947],"iteration":346,"passed_time":0.5117335769,"remaining_time":0.9630029559},
{"learn":[4.305137856],"iteration":347,"passed_time":0.5126703694,"remaining_time":0.9605203472},
{"learn":[4.304787172],"iteration":348,"passed_time":0.5147573558,"remaining_time":0.9601920878},
{"learn":[4.30350134],"iteration":349,"passed_time":0.5170430774,"remaining_time":0.9602228581},
{"learn":[4.30293809],"iteration":350,"passed_time":0.5179283898,"remaining_time":0.9576510684},
{"learn":[4.299548459],"iteration":351,"passed_time":0.5189815888,"remaining_time":0.9553979248},
{"learn":[4.294768408],"iteration":352,"passed_time":0.519758227,"remaining_time":0.9526446824},
{"learn":[4.294581479],"iteration":353,"passed_time":0.5204846859,"remaining_time":0.949811037},
{"learn":[4.292551604],"iteration":354,"passed_time":0.5220061299,"remaining_time":0.9484336726},
{"learn":[4.288628894],"iteration":355,"passed_time":0.5228239749,"remaining_time":0.9457826962},
{"learn":[4.287802767],"iteration":356,"passed_time":0.5234943355,"remaining_time":0.9428763522},
{"learn":[4.284566905],"iteration":357,"passed_time":0.5241841109,"remaining_time":0.9400173162},
{"learn":[4.27890232],"iteration":358,"passed_time":0.5248826782,"remaining_time":0.9371860633},
{"learn":[4.276938023],"iteration":359,"passed_time":0.5255656582,"remaining_time":0.9343389479},
{"learn":[4.273425094],"iteration":360,"passed_time":0.5294221048,"remaining_time":0.9371211218},
{"learn":[4.269726505],"iteration":361,"passed_time":0.5327797377,"remaining_time":0.9389874935},
{"learn":[4.265565857],"iteration":362,"passed_time":0.5347873071,"remaining_time":0.9384559631},
{"learn":[4.262117173],"iteration":363,"passed_time":0.5356612765,"remaining_time":0.9359356369},
{"learn":[4.259185148],"iteration":364,"passed_time":0.5364083997,"remaining_time":0.9332036543},
{"learn":[4.257668507],"iteration":365,"passed_time":0.5372024066,"remaining_time":0.9305637317},
{"learn":[4.253432436],"iteration":366,"passed_time":0.5388114369,"remaining_time":0.9293396174},
{"learn":[4.250216667],"iteration":367,"passed_time":0.5402128637,"remaining_time":0.9277568747},
{"learn":[4.24514828],"iteration":368,"passed_time":0.5411447985,"remaining_time":0.9253722707},
{"learn":[4.244015772],"iteration":369,"passed_time":0.5431560711,"remaining_time":0.9248333102},
{"learn":[4.240329192],"iteration":370,"passed_time":0.5451711778,"remaining_time":0.9242929133},
{"learn":[4.236718014],"iteration":371,"passed_time":0.5466433491,"remaining_time":0.9228280194},
{"learn":[4.233495944],"iteration":372,"passed_time":0.5475265423,"remaining_time":0.9203730349},
{"learn":[4.230357491],"iteration":373,"passed_time":0.5481817853,"remaining_time":0.9175449134},
{"learn":[4.227381215],"iteration":374,"passed_time":0.5487966198,"remaining_time":0.914661033},
{"learn":[4.226169067],"iteration":375,"passed_time":0.5494030263,"remaining_time":0.9117752351},
{"learn":[4.225963861],"iteration":376,"passed_time":0.5500630766,"remaining_time":0.9089901769},
{"learn":[4.224346548],"iteration":377,"passed_time":0.5507813217,"remaining_time":0.9063121219},
{"learn":[4.222595381],"iteration":378,"passed_time":0.5515031598,"remaining_time":0.9036502962},
{"learn":[4.219700938],"iteration":379,"passed_time":0.5523911133,"remaining_time":0.9012697111},
{"learn":[4.216356207],"iteration":380,"passed_time":0.553119278,"remaining_time":0.8986373571},
{"learn":[4.214326494],"iteration":381,"passed_time":0.5537320185,"remaining_time":0.8958282393},
{"learn":[4.212901398],"iteration":382,"passed_time":0.5543684929,"remaining_time":0.8930688253},
{"learn":[4.211331091],"iteration":383,"passed_time":0.5549842651,"remaining_time":0.8902872587},
{"learn":[4.208624791],"iteration":384,"passed_time":0.5578621478,"remaining_time":0.8911304439},
{"learn":[4.204659106],"iteration":385,"passed_time":0.5595157099,"remaining_time":0.8900068546},
{"learn":[4.202968852],"iteration":386,"passed_time":0.5604303197,"remaining_time":0.8877100413},
{"learn":[4.197261935],"iteration":387,"passed_time":0.5613714842,"remaining_time":0.885462238},
{"learn":[4.196934403],"iteration":388,"passed_time":0.5621763897,"remaining_time":0.8830071313},
{"learn":[4.192479929],"iteration":389,"passed_time":0.5629282428,"remaining_time":0.880477508},
{"learn":[4.190243116],"iteration":390,"passed_time":0.563773698,"remaining_time":0.8781027674},
{"learn":[4.185852431],"iteration":391,"passed_time":0.5646997667,"remaining_time":0.8758608627},
{"learn":[4.180967944],"iteration":392,"passed_time":0.5654243106,"remaining_time":0.8733143933},
{"learn":[4.178283162],"iteration":393,"passed_time":0.5660379956,"remaining_time":0.8706066633},
{"learn":[4.176341157],"iteration":394,"passed_time":0.5667269635,"remaining_time":0.8680248429},
{"learn":[4.176041504],"iteration":395,"passed_time":0.5673184936,"remaining_time":0.8653039649},
{"learn":[4.175564513],"iteration":396,"passed_time":0.5678936523,"remaining_time":0.862568948},
{"learn":[4.170830274],"iteration":397,"passed_time":0.5686409553,"remaining_time":0.8601051636},
{"learn":[4.167804808],"iteration":398,"passed_time":0.5695189841,"remaining_time":0.8578468909},
{"learn":[4.165860548],"iteration":399,"passed_time":0.5713184727,"remaining_time":0.8569777091},
{"learn":[4.160950571],"iteration":400,"passed_time":0.5723540148,"remaining_time":0.8549627303},
{"learn":[4.158544115],"iteration":401,"passed_time":0.5732264691,"remaining_time":0.8527100212},
{"learn":[4.154448767],"iteration":402,"passed_time":0.5740207887,"remaining_time":0.850348414},
{"learn":[4.15197457],"iteration":403,"passed_time":0.5749025475,"remaining_time":0.8481235602},
{"learn":[4.149562679],"iteration":404,"passed_time":0.5758664014,"remaining_time":0.8460259477},
{"learn":[4.149327961],"iteration":405,"passed_time":0.5767293235,"remaining_time":0.8437862517},
{"learn":[4.147444889],"iteration":406,"passed_time":0.5780405087,"remaining_time":0.8422064414},
{"learn":[4.147254809],"iteration":407,"passed_time":0.579612616,"remaining_time":0.8410065408},
{"learn":[4.144589165],"iteration":408,"passed_time":0.5812387856,"remaining_time":0.8398829395},
{"learn":[4.141691034],"iteration":409,"passed_time":0.5852162501,"remaining_time":0.8421404575},
{"learn":[4.138893468],"iteration":410,"passed_time":0.5865812363,"remaining_time":0.8406237181},
{"learn":[4.136964597],"iteration":411,"passed_time":0.5874999912,"remaining_time":0.8384708612},
{"learn":[4.133773523],"iteration":412,"passed_time":0.5882365125,"remaining_time":0.8360649706},
{"learn":[4.131363444],"iteration":413,"passed_time":0.5889366797,"remaining_time":0.8336156868},
{"learn":[4.130228592],"iteration":414,"passed_time":0.589940722,"remaining_time":0.8316031864},
{"learn":[4.12884186],"iteration":415,"passed_time":0.5906108532,"remaining_time":0.8291267746},
{"learn":[4.12413494],"iteration":416,"passed_time":0.5912233105,"remaining_time":0.8265783934},
{"learn":[4.119422508],"iteration":417,"passed_time":0.5918319891,"remaining_time":0.8240340135},
{"learn":[4.117038244],"iteration":418,"passed_time":0.5924343235,"remaining_time":0.8214900763},
{"learn":[4.116067631],"iteration":419,"passed_time":0.5930374865,"remaining_time":0.8189565289},
{"learn":[4.110343455],"iteration":420,"passed_time":0.5936426115,"remaining_time":0.8164348505},
{"learn":[4.105604544],"iteration":421,"passed_time":0.594231114,"remaining_time":0.8138994879},
{"learn":[4.103390131],"iteration":422,"passed_time":0.594813716,"remaining_time":0.8113652816},
{"learn":[4.096724402],"iteration":423,"passed_time":0.5955858301,"remaining_time":0.8090977315},
{"learn":[4.093431279],"iteration":424,"passed_time":0.5967643308,"remaining_time":0.8073870358},
{"learn":[4.091412744],"iteration":425,"passed_time":0.5995679826,"remaining_time":0.8078685963},
{"learn":[4.091192901],"iteration":426,"passed_time":0.6010947876,"remaining_time":0.8066213426},
{"learn":[4.088994581],"iteration":427,"passed_time":0.601896847,"remaining_time":0.8044041974},
{"learn":[4.087845355],"iteration":428,"passed_time":0.6025596778,"remaining_time":0.8020083358},
{"learn":[4.083650279],"iteration":429,"passed_time":0.6032456047,"remaining_time":0.7996511504},
{"learn":[4.079840652],"iteration":430,"passed_time":0.6039477617,"remaining_time":0.7973231471},
{"learn":[4.075707828],"iteration":431,"passed_time":0.6046033417,"remaining_time":0.7949414307},
{"learn":[4.071345409],"iteration":432,"passed_time":0.605291055,"remaining_time":0.7926097649},
{"learn":[4.067460475],"iteration":433,"passed_time":0.606024711,"remaining_time":0.7903455908},
{"learn":[4.064914749],"iteration":434,"passed_time":0.6066800691,"remaining_time":0.7879867564},
{"learn":[4.063823175],"iteration":435,"passed_time":0.6073705134,"remaining_time":0.7856811228},
{"learn":[4.058898471],"iteration":436,"passed_time":0.6081175635,"remaining_time":0.7834558083},
{"learn":[4.054120355],"iteration":437,"passed_time":0.6087709629,"remaining_time":0.7811170803},
{"learn":[4.052715901],"iteration":438,"passed_time":0.6095754407,"remaining_time":0.7789790939},
{"learn":[4.052114167],"iteration":439,"passed_time":0.6102263302,"remaining_time":0.7766516929},
{"learn":[4.051377267],"iteration":440,"passed_time":0.6109165123,"remaining_time":0.7743817015},
{"learn":[4.049275336],"iteration":441,"passed_time":0.6115207138,"remaining_time":0.7720103129},
{"learn":[4.047099198],"iteration":442,"passed_time":0.6128569126,"remaining_time":0.7705672693},
{"learn":[4.044348685],"iteration":443,"passed_time":0.6145755867,"remaining_time":0.7696036626},
{"learn":[4.042822379],"iteration":444,"passed_time":0.6160055924,"remaining_time":0.7682766378},
{"learn":[4.041258611],"iteration":445,"passed_time":0.6170001067,"remaining_time":0.7664082043},
{"learn":[4.040044254],"iteration":446,"passed_time":0.6177296419,"remaining_time":0.7642158657},
{"learn":[4.036860137],"iteration":447,"passed_time":0.6185017233,"remaining_time":0.7620824804},
{"learn":[4.036372284],"iteration":448,"passed_time":0.6191646129,"remaining_time":0.7598211619},
{"learn":[4.03368231],"iteration":449,"passed_time":0.6199017039,"remaining_time":0.7576576381},
{"learn":[4.032439519],"iteration":450,"passed_time":0.6205912751,"remaining_time":0.7554425943},
{"learn":[4.032008634],"iteration":451,"passed_time":0.6211805742,"remaining_time":0.7531127315},
{"learn":[4.030034932],"iteration":452,"passed_time":0.6218937608,"remaining_time":0.7509401482},
{"learn":[4.028173412],"iteration":453,"passed_time":0.6226345348,"remaining_time":0.7488071718},
{"learn":[4.023806097],"iteration":454,"passed_time":0.6237977927,"remaining_time":0.7471863671},
{"learn":[4.020239186],"iteration":455,"passed_time":0.624502258,"remaining_time":0.7450202376},
{"learn":[4.017384838],"iteration":456,"passed_time":0.6251695692,"remaining_time":0.742816359},
{"learn":[4.016468229],"iteration":457,"passed_time":0.6259859697,"remaining_time":0.7407956236},
{"learn":[4.014530169],"iteration":458,"passed_time":0.6266714731,"remaining_time":0.7386258539},
{"learn":[4.012884822],"iteration":459,"passed_time":0.6295140327,"remaining_time":0.7389947341},
{"learn":[4.008924707],"iteration":460,"passed_time":0.6308977202,"remaining_time":0.7376439722},
{"learn":[4.008286778],"iteration":461,"passed_time":0.6317273587,"remaining_time":0.7356478765},
{"learn":[4.006444202],"iteration":462,"passed_time":0.6324435736,"remaining_time":0.7335252679},
{"learn":[4.003284363],"iteration":463,"passed_time":0.6331631607,"remaining_time":0.7314126167},
{"learn":[3.999811484],"iteration":464,"passed_time":0.6340375418,"remaining_time":0.7294840535},
{"learn":[3.997483319],"iteration":465,"passed_time":0.6347137273,"remaining_time":0.7273328978},
{"learn":[3.99708333],"iteration":466,"passed_time":0.63556141,"remaining_time":0.7253837934},
{"learn":[3.995860263],"iteration":467,"passed_time":0.6362471075,"remaining_time":0.7232552589},
{"learn":[3.994131111],"iteration":468,"passed_time":0.6374889111,"remaining_time":0.7217624985},
{"learn":[3.993125499],"iteration":469,"passed_time":0.6395332783,"remaining_time":0.7211758244},
{"learn":[3.992954084],"iteration":470,"passed_time":0.6402483353,"remaining_time":0.7190899562},
{"learn":[3.990635743],"iteration":471,"passed_time":0.6409449481,"remaining_time":0.716989264},
{"learn":[3.986678254],"iteration":472,"passed_time":0.6420228935,"remaining_time":0.7153193761},
{"learn":[3.986393291],"iteration":473,"passed_time":0.6435744575,"remaining_time":0.7141775625},
{"learn":[3.986152671],"iteration":474,"passed_time":0.6446652357,"remaining_time":0.7125247342},
{"learn":[3.985596662],"iteration":475,"passed_time":0.6456260805,"remaining_time":0.7107312315},
{"learn":[3.983853457],"iteration":476,"passed_time":0.6463087253,"remaining_time":0.7086361914},
{"learn":[3.983263928],"iteration":477,"passed_time":0.6469828714,"remaining_time":0.70653778},
{"learn":[3.980067202],"iteration":478,"passed_time":0.6476651119,"remaining_time":0.7044541196},
{"learn":[3.978115407],"iteration":479,"passed_time":0.6483161552,"remaining_time":0.7023425014},
{"learn":[3.972661644],"iteration":480,"passed_time":0.6490109042,"remaining_time":0.7002841149},
{"learn":[3.969938254],"iteration":481,"passed_time":0.6497872274,"remaining_time":0.6983190535},
{"learn":[3.968211434],"iteration":482,"passed_time":0.650809266,"remaining_time":0.6966219265},
{"learn":[3.966113368],"iteration":483,"passed_time":0.6515016118,"remaining_time":0.6945760986},
{"learn":[3.962246044],"iteration":484,"passed_time":0.6521591387,"remaining_time":0.6924988793},
{"learn":[3.961319703],"iteration":485,"passed_time":0.6528595345,"remaining_time":0.690472841},
{"learn":[3.96078191],"iteration":486,"passed_time":0.6535501796,"remaining_time":0.6884419756},
{"learn":[3.958913633],"iteration":487,"passed_time":0.654275647,"remaining_time":0.6864531378},
{"learn":[3.957428286],"iteration":488,"passed_time":0.654964535,"remaining_time":0.6844312421},
{"learn":[3.952641965],"iteration":489,"passed_time":0.655722871,"remaining_time":0.6824870698},
{"learn":[3.951486786],"iteration":490,"passed_time":0.6571348165,"remaining_time":0.6812252986},
{"learn":[3.94938344],"iteration":491,"passed_time":0.6583776041,"remaining_time":0.6797882579},
{"learn":[3.947297924],"iteration":492,"passed_time":0.6593759315,"remaining_time":0.678100603},
{"learn":[3.946284886],"iteration":493,"passed_time":0.6600904382,"remaining_time":0.6761250238},
{"learn":[3.943288204],"iteration":494,"passed_time":0.6606838144,"remaining_time":0.6740309621},
{"learn":[3.943076488],"iteration":495,"passed_time":0.6613320065,"remaining_time":0.6719986518},
{"learn":[3.942347078],"iteration":496,"passed_time":0.6620127152,"remaining_time":0.6700048205},
{"learn":[3.940251541],"iteration":497,"passed_time":0.6626637106,"remaining_time":0.6679863107},
{"learn":[3.939011019],"iteration":498,"passed_time":0.6636117755,"remaining_time":0.6662715422},
{"learn":[3.938760512],"iteration":499,"passed_time":0.6642452316,"remaining_time":0.6642452316},
{"learn":[3.934522727],"iteration":500,"passed_time":0.6649701419,"remaining_time":0.6623155705},
{"learn":[3.930091193],"iteration":501,"passed_time":0.6657368051,"remaining_time":0.6604321294},
{"learn":[3.927671752],"iteration":502,"passed_time":0.6664157013,"remaining_time":0.6584664087},
{"learn":[3.927280041],"iteration":503,"passed_time":0.6670740778,"remaining_time":0.6564856003},
{"learn":[3.925987561],"iteration":504,"passed_time":0.6677622348,"remaining_time":0.6545392202},
{"learn":[3.921645957],"iteration":505,"passed_time":0.668434928,"remaining_time":0.6525827163},
{"learn":[3.920333743],"iteration":506,"passed_time":0.6690353113,"remaining_time":0.6505609634},
{"learn":[3.918659461],"iteration":507,"passed_time":0.6697511145,"remaining_time":0.6486565912},
{"learn":[3.916124385],"iteration":508,"passed_time":0.6703924172,"remaining_time":0.6466850233},
{"learn":[3.913849268],"iteration":509,"passed_time":0.6726868383,"remaining_time":0.6463069623},
{"learn":[3.912826119],"iteration":510,"passed_time":0.6739510069,"remaining_time":0.6449355037},
{"learn":[3.910034145],"iteration":511,"passed_time":0.6747517437,"remaining_time":0.6431227557},
{"learn":[3.90792379],"iteration":512,"passed_time":0.6754070397,"remaining_time":0.6411758837},
{"learn":[3.907823851],"iteration":513,"passed_time":0.6761046087,"remaining_time":0.6392740075},
{"learn":[3.904527401],"iteration":514,"passed_time":0.6767111597,"remaining_time":0.6372910921},
{"learn":[3.903378283],"iteration":515,"passed_time":0.6777774873,"remaining_time":0.6357447749},
{"learn":[3.902170135],"iteration":516,"passed_time":0.6784926099,"remaining_time":0.6338722061},
{"learn":[3.899435429],"iteration":517,"passed_time":0.6791283927,"remaining_time":0.6319302805},
{"learn":[3.897497505],"iteration":518,"passed_time":0.6798316362,"remaining_time":0.6300559095},
{"learn":[3.896426119],"iteration":519,"passed_time":0.6804683072,"remaining_time":0.6281245913},
{"learn":[3.896044669],"iteration":520,"passed_time":0.681227823,"remaining_time":0.6263111847},
{"learn":[3.892795942],"iteration":521,"passed_time":0.6818745329,"remaining_time":0.6243985186},
{"learn":[3.892413888],"iteration":522,"passed_time":0.6825726196,"remaining_time":0.6225375517},
{"learn":[3.891738985],"iteration":523,"passed_time":0.683254261,"remaining_time":0.6206660844},
{"learn":[3.88822057],"iteration":524,"passed_time":0.6839000256,"remaining_time":0.6187666898},
{"learn":[3.883837053],"iteration":525,"passed_time":0.6845985265,"remaining_time":0.6169195847},
{"learn":[3.881769742],"iteration":526,"passed_time":0.6852956754,"remaining_time":0.6150756252},
{"learn":[3.880356898],"iteration":527,"passed_time":0.6873477657,"remaining_time":0.6144472451},
{"learn":[3.879250273],"iteration":528,"passed_time":0.6889387575,"remaining_time":0.6134029391},
{"learn":[3.877174493],"iteration":529,"passed_time":0.6898717335,"remaining_time":0.6117730467},
{"learn":[3.875854201],"iteration":530,"passed_time":0.6906202339,"remaining_time":0.6099828431},
{"learn":[3.873189396],"iteration":531,"passed_time":0.6917050831,"remaining_time":0.6084924415},
{"learn":[3.871583368],"iteration":532,"passed_time":0.6930126609,"remaining_time":0.6071987104},
{"learn":[3.869622679],"iteration":533,"passed_time":0.6937847859,"remaining_time":0.6054376596},
{"learn":[3.866860164],"iteration":534,"passed_time":0.6945246348,"remaining_time":0.6036522527},
{"learn":[3.864498444],"iteration":535,"passed_time":0.6952221257,"remaining_time":0.601834079},
{"learn":[3.861416322],"iteration":536,"passed_time":0.6960059702,"remaining_time":0.600094533},
{"learn":[3.860265769],"iteration":537,"passed_time":0.6966441151,"remaining_time":0.5982334223},
{"learn":[3.859328725],"iteration":538,"passed_time":0.6972788358,"remaining_time":0.5963739208},
{"learn":[3.858521278],"iteration":539,"passed_time":0.6978997498,"remaining_time":0.5945071943},
{"learn":[3.85599111],"iteration":540,"passed_time":0.6985151238,"remaining_time":0.5926403731},
{"learn":[3.852379816],"iteration":541,"passed_time":0.6992859918,"remaining_time":0.590909565},
{"learn":[3.851327537],"iteration":542,"passed_time":0.7003783708,"remaining_time":0.5894528829},
{"learn":[3.847854898],"iteration":543,"passed_time":0.7021581211,"remaining_time":0.5885737191},
{"learn":[3.847083414],"iteration":544,"passed_time":0.7033661452,"remaining_time":0.5872139377},
{"learn":[3.845397429],"iteration":545,"passed_time":0.7042085761,"remaining_time":0.5855507208},
{"learn":[3.841933528],"iteration":546,"passed_time":0.7056044268,"remaining_time":0.5843488214},
{"learn":[3.840996474],"iteration":547,"passed_time":0.7065453728,"remaining_time":0.5827710009},
{"learn":[3.838355966],"iteration":548,"passed_time":0.7073184507,"remaining_time":0.581057598},
{"learn":[3.83342799],"iteration":549,"passed_time":0.7079451215,"remaining_time":0.5792278267},
{"learn":[3.828161535],"iteration":550,"passed_time":0.7085505583,"remaining_time":0.5773851192},
{"learn":[3.823502399],"iteration":551,"passed_time":0.7091495971,"remaining_time":0.575541702},
{"learn":[3.820068862],"iteration":552,"passed_time":0.7097774006,"remaining_time":0.5737260363},
{"learn":[3.817951642],"iteration":553,"passed_time":0.7104266204,"remaining_time":0.5719319002},
{"learn":[3.815785958],"iteration":554,"passed_time":0.7111490661,"remaining_time":0.5702006026},
{"learn":[3.81503012],"iteration":555,"passed_time":0.7117796031,"remaining_time":0.5683995392},
{"learn":[3.813529315],"iteration":556,"passed_time":0.7124250492,"remaining_time":0.5666145364},
{"learn":[3.808881326],"iteration":557,"passed_time":0.7130532678,"remaining_time":0.564819972},
{"learn":[3.808740434],"iteration":558,"passed_time":0.7136434828,"remaining_time":0.5629995991},
{"learn":[3.80714352],"iteration":559,"passed_time":0.714227746,"remaining_time":0.5611789433},
{"learn":[3.80573346],"iteration":560,"passed_time":0.7167599579,"remaining_time":0.5608870259},
{"learn":[3.803370052],"iteration":561,"passed_time":0.7187515879,"remaining_time":0.5601658283},
{"learn":[3.803215211],"iteration":562,"passed_time":0.7195550338,"remaining_time":0.5585178504},
{"learn":[3.801309667],"iteration":563,"passed_time":0.7202277749,"remaining_time":0.556771826},
{"learn":[3.800003847],"iteration":564,"passed_time":0.7208476662,"remaining_time":0.5549889112},
{"learn":[3.798026138],"iteration":565,"passed_time":0.7214495477,"remaining_time":0.5531962963},
{"learn":[3.794745847],"iteration":566,"passed_time":0.7220770941,"remaining_time":0.551427481},
{"learn":[3.794312041],"iteration":567,"passed_time":0.7227601943,"remaining_time":0.5497049365},
{"learn":[3.792205926],"iteration":568,"passed_time":0.7234958904,"remaining_time":0.5480258854},
{"learn":[3.788991061],"iteration":569,"passed_time":0.7241480135,"remaining_time":0.5462870979},
{"learn":[3.787391572],"iteration":570,"passed_time":0.7247592533,"remaining_time":0.5445214004},
{"learn":[3.7826445],"iteration":571,"passed_time":0.7254113284,"remaining_time":0.5427902947},
{"learn":[3.781700331],"iteration":572,"passed_time":0.7260172802,"remaining_time":0.5410285841},
{"learn":[3.780045374],"iteration":573,"passed_time":0.7266435468,"remaining_time":0.5392859773},
{"learn":[3.775462644],"iteration":574,"passed_time":0.7272672934,"remaining_time":0.5375453908},
{"learn":[3.773711943],"iteration":575,"passed_time":0.7279322989,"remaining_time":0.5358390533},
{"learn":[3.772415806],"iteration":576,"passed_time":0.7285494383,"remaining_time":0.5341012347},
{"learn":[3.770170875],"iteration":577,"passed_time":0.7292316335,"remaining_time":0.5324147912},
{"learn":[3.765166479],"iteration":578,"passed_time":0.730869473,"remaining_time":0.5314266807},
{"learn":[3.763976102],"iteration":579,"passed_time":0.7324337228,"remaining_time":0.5303830406},
{"learn":[3.760761708],"iteration":580,"passed_time":0.733364424,"remaining_time":0.528880712},
{"learn":[3.758155662],"iteration":581,"passed_time":0.7340713749,"remaining_time":0.5272196472},
{"learn":[3.756844548],"iteration":582,"passed_time":0.7347402297,"remaining_time":0.5255346068},
{"learn":[3.753098923],"iteration":583,"passed_time":0.7354611998,"remaining_time":0.5238901697},
{"learn":[3.751618946],"iteration":584,"passed_time":0.7360835978,"remaining_time":0.5221789625},
{"learn":[3.751398464],"iteration":585,"passed_time":0.7366713381,"remaining_time":0.5204469863},
{"learn":[3.749920103],"iteration":586,"passed_time":0.7372719104,"remaining_time":0.518727937},
{"learn":[3.748237465],"iteration":587,"passed_time":0.7378713677,"remaining_time":0.5170119107},
{"learn":[3.746021536],"iteration":588,"passed_time":0.7384546411,"remaining_time":0.5152883829},
{"learn":[3.74417648],"iteration":589,"passed_time":0.7390590132,"remaining_time":0.5135833821},
{"learn":[3.738788389],"iteration":590,"passed_time":0.7396914559,"remaining_time":0.5119015321},
{"learn":[3.736021611],"iteration":591,"passed_time":0.7403125237,"remaining_time":0.510215388},
{"learn":[3.734546151],"iteration":592,"passed_time":0.7409869269,"remaining_time":0.5085694422},
{"learn":[3.733527479],"iteration":593,"passed_time":0.7416248348,"remaining_time":0.5069018231},
{"learn":[3.733026392],"iteration":594,"passed_time":0.7422575876,"remaining_time":0.5052341563},
{"learn":[3.730314752],"iteration":595,"passed_time":0.7429182093,"remaining_time":0.5035888533},
{"learn":[3.727342596],"iteration":596,"passed_time":0.7449902361,"remaining_time":0.5028996066},
{"learn":[3.725459604],"iteration":597,"passed_time":0.745881491,"remaining_time":0.5014119722},
{"learn":[3.723158842],"iteration":598,"passed_time":0.7467515363,"remaining_time":0.4999121303},
{"learn":[3.722362756],"iteration":599,"passed_time":0.7474554487,"remaining_time":0.4983036324},
{"learn":[3.721443615],"iteration":600,"passed_time":0.7480426848,"remaining_time":0.4966206843},
{"learn":[3.720743486],"iteration":601,"passed_time":0.7486828985,"remaining_time":0.4949764013},
{"learn":[3.720215334],"iteration":602,"passed_time":0.7493057073,"remaining_time":0.4933239897},
{"learn":[3.719436563],"iteration":603,"passed_time":0.7499175672,"remaining_time":0.491667809},
{"learn":[3.715046574],"iteration":604,"passed_time":0.7505766344,"remaining_time":0.4900459018},
{"learn":[3.71443396],"iteration":605,"passed_time":0.7511845071,"remaining_time":0.4883938875},
{"learn":[3.712938941],"iteration":606,"passed_time":0.7517866214,"remaining_time":0.4867415852},
{"learn":[3.712814764],"iteration":607,"passed_time":0.7523932488,"remaining_time":0.4850956473},
{"learn":[3.71235348],"iteration":608,"passed_time":0.7530132293,"remaining_time":0.4834616956},
{"learn":[3.711223749],"iteration":609,"passed_time":0.753725563,"remaining_time":0.481890114},
{"learn":[3.710755648],"iteration":610,"passed_time":0.7543302267,"remaining_time":0.4802527957},
{"learn":[3.708668039],"iteration":611,"passed_time":0.7549552043,"remaining_time":0.4786317308},
{"learn":[3.705623591],"iteration":612,"passed_time":0.7555792811,"remaining_time":0.4770133471},
{"learn":[3.704045802],"iteration":613,"passed_time":0.7561625604,"remaining_time":0.4753725542},
{"learn":[3.699915209],"iteration":614,"passed_time":0.7568573296,"remaining_time":0.4738049949},
{"learn":[3.696182221],"iteration":615,"passed_time":0.7574812568,"remaining_time":0.4721961082},
{"learn":[3.694263278],"iteration":616,"passed_time":0.7592065818,"remaining_time":0.4712741018},
{"learn":[3.693810229],"iteration":617,"passed_time":0.7603652047,"remaining_time":0.4699992042},
{"learn":[3.690900932],"iteration":618,"passed_time":0.7614322264,"remaining_time":0.4686683009},
{"learn":[3.688020895],"iteration":619,"passed_time":0.7621174592,"remaining_time":0.4671042492},
{"learn":[3.685491894],"iteration":620,"passed_time":0.7627481003,"remaining_time":0.4655097102},
{"learn":[3.684328128],"iteration":621,"passed_time":0.7633929725,"remaining_time":0.463926919},
{"learn":[3.680640153],"iteration":622,"passed_time":0.7640300948,"remaining_time":0.462342449},
{"learn":[3.678932783],"iteration":623,"passed_time":0.7646763181,"remaining_time":0.4607664994},
{"learn":[3.674167041],"iteration":624,"passed_time":0.7654073003,"remaining_time":0.4592443802},
{"learn":[3.672200976],"iteration":625,"passed_time":0.7661573141,"remaining_time":0.4577361589},
{"learn":[3.670606604],"iteration":626,"passed_time":0.7667910929,"remaining_time":0.4561612084},
{"learn":[3.665506042],"iteration":627,"passed_time":0.7673788954,"remaining_time":0.4545620208},
{"learn":[3.664214007],"iteration":628,"passed_time":0.7679957012,"remaining_time":0.452983156},
{"learn":[3.66261643],"iteration":629,"passed_time":0.768592494,"remaining_time":0.4513955917},
{"learn":[3.662118449],"iteration":630,"passed_time":0.7691970812,"remaining_time":0.4498157258},
{"learn":[3.660871366],"iteration":631,"passed_time":0.7698133467,"remaining_time":0.4482457462},
{"learn":[3.656695243],"iteration":632,"passed_time":0.7704255713,"remaining_time":0.4466764371},
{"learn":[3.654497801],"iteration":633,"passed_time":0.7710615642,"remaining_time":0.4451238683},
{"learn":[3.654189134],"iteration":634,"passed_time":0.772144516,"remaining_time":0.4438310998},
{"learn":[3.653957699],"iteration":635,"passed_time":0.7751727611,"remaining_time":0.443652335},
{"learn":[3.651920725],"iteration":636,"passed_time":0.7763244046,"remaining_time":0.4423952258},
{"learn":[3.65106705],"iteration":637,"passed_time":0.7772192903,"remaining_time":0.4409927635},
{"learn":[3.650612844],"iteration":638,"passed_time":0.7780925488,"remaining_time":0.4395796716},
{"learn":[3.649884732],"iteration":639,"passed_time":0.7788502201,"remaining_time":0.4381032488},
{"learn":[3.646276182],"iteration":640,"passed_time":0.7798924987,"remaining_time":0.4367884665},
{"learn":[3.645808194],"iteration":641,"passed_time":0.7805555724,"remaining_time":0.4352630762},
{"learn":[3.645042989],"iteration":642,"passed_time":0.7811772964,"remaining_time":0.4337174103},
{"learn":[3.639864499],"iteration":643,"passed_time":0.7817927233,"remaining_time":0.4321711328},
{"learn":[3.637318478],"iteration":644,"passed_time":0.7824074015,"remaining_time":0.4306273295},
{"learn":[3.636344905],"iteration":645,"passed_time":0.7830059749,"remaining_time":0.4290775776},
{"learn":[3.634754643],"iteration":646,"passed_time":0.7836025693,"remaining_time":0.4275296862},
{"learn":[3.630724975],"iteration":647,"passed_time":0.7842969747,"remaining_time":0.4260378628},
{"learn":[3.629408252],"iteration":648,"passed_time":0.7855117017,"remaining_time":0.4248299034},
{"learn":[3.62790646],"iteration":649,"passed_time":0.7864815788,"remaining_time":0.4234900809},
{"learn":[3.627388973],"iteration":650,"passed_time":0.7893460438,"remaining_time":0.4231670803},
{"learn":[3.625163557],"iteration":651,"passed_time":0.7908981195,"remaining_time":0.4221358061},
{"learn":[3.623701985],"iteration":652,"passed_time":0.7920793831,"remaining_time":0.4209058896},
{"learn":[3.622342639],"iteration":653,"passed_time":0.7927974895,"remaining_time":0.4194310877},
{"learn":[3.621130639],"iteration":654,"passed_time":0.7938426663,"remaining_time":0.41813087},
{"learn":[3.619125665],"iteration":655,"passed_time":0.7945244951,"remaining_time":0.4166408938},
{"learn":[3.618878783],"iteration":656,"passed_time":0.7952381817,"remaining_time":0.4151700096},
{"learn":[3.616207429],"iteration":657,"passed_time":0.7959627138,"remaining_time":0.413707064},
{"learn":[3.61206486],"iteration":658,"passed_time":0.7966445376,"remaining_time":0.41222426},
{"learn":[3.611955873],"iteration":659,"passed_time":0.7975142274,"remaining_time":0.4108406626},
{"learn":[3.610713743],"iteration":660,"passed_time":0.7983663115,"remaining_time":0.4094495909},
{"learn":[3.610044025],"iteration":661,"passed_time":0.7995281586,"remaining_time":0.4082183045},
{"learn":[3.607342669],"iteration":662,"passed_time":0.8006668616,"remaining_time":0.4069754636},
{"learn":[3.602510618],"iteration":663,"passed_time":0.8014529287,"remaining_time":0.4055544941},
{"learn":[3.600492392],"iteration":664,"passed_time":0.8033758267,"remaining_time":0.4047081232},
{"learn":[3.597171065],"iteration":665,"passed_time":0.805528605,"remaining_time":0.4039738049},
{"learn":[3.594358798],"iteration":666,"passed_time":0.8064551015,"remaining_time":0.4026230117},
{"learn":[3.593945251],"iteration":667,"passed_time":0.8071904733,"remaining_time":0.4011784987},
{"learn":[3.593607748],"iteration":668,"passed_time":0.808352659,"remaining_time":0.3999472797},
{"learn":[3.592238714],"iteration":669,"passed_time":0.8091583375,"remaining_time":0.3985406737},
{"learn":[3.590144654],"iteration":670,"passed_time":0.810040819,"remaining_time":0.3971735163},
{"learn":[3.587151536],"iteration":671,"passed_time":0.8107531645,"remaining_time":0.3957247589},
{"learn":[3.586070865],"iteration":672,"passed_time":0.8113990249,"remaining_time":0.3942458858},
{"learn":[3.585102746],"iteration":673,"passed_time":0.81256336,"remaining_time":0.3930202602},
{"learn":[3.584362847],"iteration":674,"passed_time":0.8132559411,"remaining_time":0.3915676754},
{"learn":[3.581407561],"iteration":675,"passed_time":0.8138770484,"remaining_time":0.3900830824},
{"learn":[3.57919422],"iteration":676,"passed_time":0.8145572412,"remaining_time":0.3886292303},
{"learn":[3.577632204],"iteration":677,"passed_time":0.8152488921,"remaining_time":0.3871831021},
{"learn":[3.573911195],"iteration":678,"passed_time":0.816133749,"remaining_time":0.3858305353},
{"learn":[3.573408216],"iteration":679,"passed_time":0.8180890871,"remaining_time":0.3849830998},
{"learn":[3.571076482],"iteration":680,"passed_time":0.8196760044,"remaining_time":0.3839598317},
{"learn":[3.568177107],"iteration":681,"passed_time":0.8206563313,"remaining_time":0.3826520724},
{"learn":[3.564824621],"iteration":682,"passed_time":0.821987185,"remaining_time":0.3815079614},
{"learn":[3.562475026],"iteration":683,"passed_time":0.822859594,"remaining_time":0.3801515083},
{"learn":[3.561226889],"iteration":684,"passed_time":0.8234902939,"remaining_time":0.3786853176},
{"learn":[3.559383467],"iteration":685,"passed_time":0.8241302984,"remaining_time":0.3772258217},
{"learn":[3.555209766],"iteration":686,"passed_time":0.8247092846,"remaining_time":0.3757409113},
{"learn":[3.55345383],"iteration":687,"passed_time":0.8256570227,"remaining_time":0.3744258591},
{"learn":[3.552300968],"iteration":688,"passed_time":0.826334545,"remaining_time":0.3729899035},
{"learn":[3.551253986],"iteration":689,"passed_time":0.8270110111,"remaining_time":0.3715556717},
{"learn":[3.549807725],"iteration":690,"passed_time":0.8278214625,"remaining_time":0.3701835483},
{"learn":[3.547992926],"iteration":691,"passed_time":0.8287379806,"remaining_time":0.3688602572},
{"learn":[3.545438607],"iteration":692,"passed_time":0.8294169095,"remaining_time":0.3674328878},
{"learn":[3.543313763],"iteration":693,"passed_time":0.8300546763,"remaining_time":0.3659895259},
{"learn":[3.542962896],"iteration":694,"passed_time":0.8306997569,"remaining_time":0.3645516919},
{"learn":[3.539800465],"iteration":695,"passed_time":0.8324513862,"remaining_time":0.363599456},
{"learn":[3.53953187],"iteration":696,"passed_time":0.8334468096,"remaining_time":0.3623161884},
{"learn":[3.536332425],"iteration":697,"passed_time":0.8346874965,"remaining_time":0.3611398624},
{"learn":[3.534993327],"iteration":698,"passed_time":0.8355400243,"remaining_time":0.359796205},
{"learn":[3.531637011],"iteration":699,"passed_time":0.8366490838,"remaining_time":0.358563893},
{"learn":[3.531040284],"iteration":700,"passed_time":0.8373240878,"remaining_time":0.3571467935},
{"learn":[3.529973872],"iteration":701,"passed_time":0.8379503678,"remaining_time":0.3557111248},
{"learn":[3.527325183],"iteration":702,"passed_time":0.8388709428,"remaining_time":0.3544020911},
{"learn":[3.527200815],"iteration":703,"passed_time":0.8399794015,"remaining_time":0.3531731574},
{"learn":[3.523459911],"iteration":704,"passed_time":0.8412225067,"remaining_time":0.352000907},
{"learn":[3.522729934],"iteration":705,"passed_time":0.8419217412,"remaining_time":0.3506019715},
{"learn":[3.522260582],"iteration":706,"passed_time":0.8426338959,"remaining_time":0.3492103699},
{"learn":[3.518641591],"iteration":707,"passed_time":0.8433524679,"remaining_time":0.3478233342},
{"learn":[3.516856405],"iteration":708,"passed_time":0.8440211597,"remaining_time":0.3464177115},
{"learn":[3.515083413],"iteration":709,"passed_time":0.844708515,"remaining_time":0.3450217878},
{"learn":[3.514671214],"iteration":710,"passed_time":0.8453809125,"remaining_time":0.3436217774},
{"learn":[3.512617621],"iteration":711,"passed_time":0.8487567812,"remaining_time":0.3433173497},
{"learn":[3.510747971],"iteration":712,"passed_time":0.8497260541,"remaining_time":0.3420355926},
{"learn":[3.508149266],"iteration":713,"passed_time":0.850545052,"remaining_time":0.3406945166},
{"learn":[3.504557165],"iteration":714,"passed_time":0.8513717553,"remaining_time":0.3393579724},
{"learn":[3.501367208],"iteration":715,"passed_time":0.8532407751,"remaining_time":0.3384362851},
{"learn":[3.497593362],"iteration":716,"passed_time":0.854431191,"remaining_time":0.3372441103},
{"learn":[3.496291169],"iteration":717,"passed_time":0.8551896606,"remaining_time":0.3358822901},
{"learn":[3.49330374],"iteration":718,"passed_time":0.8558842029,"remaining_time":0.3344971641},
{"learn":[3.490044385],"iteration":719,"passed_time":0.8565473681,"remaining_time":0.3331017543},
{"learn":[3.488891789],"iteration":720,"passed_time":0.8572457187,"remaining_time":0.331721991},
{"learn":[3.486869081],"iteration":721,"passed_time":0.8579607472,"remaining_time":0.330350537},
{"learn":[3.486303638],"iteration":722,"passed_time":0.8587096383,"remaining_time":0.3289938725},
{"learn":[3.486035862],"iteration":723,"passed_time":0.8596149386,"remaining_time":0.3276985125},
{"learn":[3.482668951],"iteration":724,"passed_time":0.8609779778,"remaining_time":0.3265778536},
{"learn":[3.47820549],"iteration":725,"passed_time":0.8630050964,"remaining_time":0.3257071576},
{"learn":[3.474392283],"iteration":726,"passed_time":0.8640700207,"remaining_time":0.324471961},
{"learn":[3.472268163],"iteration":727,"passed_time":0.8650677701,"remaining_time":0.3232121339},
{"learn":[3.471209164],"iteration":728,"passed_time":0.8660175551,"remaining_time":0.3219351954},
{"learn":[3.470049971],"iteration":729,"passed_time":0.8670402508,"remaining_time":0.3206861202},
{"learn":[3.469078654],"iteration":730,"passed_time":0.8679334627,"remaining_time":0.3193900157},
{"learn":[3.468643292],"iteration":731,"passed_time":0.8690302532,"remaining_time":0.3181695462},
{"learn":[3.468134848],"iteration":732,"passed_time":0.8701207944,"remaining_time":0.3169471379},
{"learn":[3.467820182],"iteration":733,"passed_time":0.871607743,"remaining_time":0.3158687461},
{"learn":[3.465776156],"iteration":734,"passed_time":0.8726198452,"remaining_time":0.3146180394},
{"learn":[3.463037608],"iteration":735,"passed_time":0.873409081,"remaining_time":0.3132880399},
{"learn":[3.45965637],"iteration":736,"passed_time":0.8765511756,"remaining_time":0.3127991305},
{"learn":[3.457275091],"iteration":737,"passed_time":0.8801519662,"remaining_time":0.3124658742},
{"learn":[3.455522955],"iteration":738,"passed_time":0.8818817909,"remaining_time":0.311462987},
{"learn":[3.451270508],"iteration":739,"passed_time":0.882922667,"remaining_time":0.3102160722},
{"learn":[3.450978947],"iteration":740,"passed_time":0.8842750556,"remaining_time":0.3090785957},
{"learn":[3.450608492],"iteration":741,"passed_time":0.8851600134,"remaining_time":0.30777801},
{"learn":[3.448122004],"iteration":742,"passed_time":0.8859903728,"remaining_time":0.3064596579},
{"learn":[3.445646714],"iteration":743,"passed_time":0.886787051,"remaining_time":0.3051310283},
{"learn":[3.44411263],"iteration":744,"passed_time":0.8875680024,"remaining_time":0.3037984438},
{"learn":[3.443264164],"iteration":745,"passed_time":0.8882328768,"remaining_time":0.302427816},
{"learn":[3.439521363],"iteration":746,"passed_time":0.8890410997,"remaining_time":0.3011076281},
{"learn":[3.436809225],"iteration":747,"passed_time":0.8935355576,"remaining_time":0.3010306959},
{"learn":[3.435509465],"iteration":748,"passed_time":0.8946406392,"remaining_time":0.2998061421},
{"learn":[3.434450277],"iteration":749,"passed_time":0.8957385842,"remaining_time":0.2985795281},
{"learn":[3.431786753],"iteration":750,"passed_time":0.8971164729,"remaining_time":0.2974460742},
{"learn":[3.430150302],"iteration":751,"passed_time":0.89819956,"remaining_time":0.2962147485},
{"learn":[3.42696281],"iteration":752,"passed_time":0.8998792373,"remaining_time":0.2951795108},
{"learn":[3.426870334],"iteration":753,"passed_time":0.900745997,"remaining_time":0.2938773412},
{"learn":[3.425200309],"iteration":754,"passed_time":0.9015932529,"remaining_time":0.292569996},
{"learn":[3.423383783],"iteration":755,"passed_time":0.9026816447,"remaining_time":0.2913416948},
{"learn":[3.422752979],"iteration":756,"passed_time":0.903331272,"remaining_time":0.2899729182},
{"learn":[3.420845924],"iteration":757,"passed_time":0.9055833133,"remaining_time":0.2891176277},
{"learn":[3.418917862],"iteration":758,"passed_time":0.9088183569,"remaining_time":0.2885707826},
{"learn":[3.417095735],"iteration":759,"passed_time":0.9109016226,"remaining_time":0.287653144},
{"learn":[3.414391848],"iteration":760,"passed_time":0.9121478932,"remaining_time":0.2864695749},
{"learn":[3.41426711],"iteration":761,"passed_time":0.9133418702,"remaining_time":0.285269508},
{"learn":[3.411976013],"iteration":762,"passed_time":0.9143522675,"remaining_time":0.2840124343},
{"learn":[3.408614844],"iteration":763,"passed_time":0.915261602,"remaining_time":0.2827247881},
{"learn":[3.407906721],"iteration":764,"passed_time":0.9159018779,"remaining_time":0.2813554788},
{"learn":[3.407494015],"iteration":765,"passed_time":0.9167790118,"remaining_time":0.2800604292},
{"learn":[3.406287128],"iteration":766,"passed_time":0.9177587067,"remaining_time":0.2787976254},
{"learn":[3.404600442],"iteration":767,"passed_time":0.9211461076,"remaining_time":0.2782628867},
{"learn":[3.404012662],"iteration":768,"passed_time":0.9223847887,"remaining_time":0.2770752746},
{"learn":[3.400398762],"iteration":769,"passed_time":0.923291504,"remaining_time":0.2757883713},
{"learn":[3.399737714],"iteration":770,"passed_time":0.9245374258,"remaining_time":0.2746032043},
{"learn":[3.399185251],"iteration":771,"passed_time":0.9253764948,"remaining_time":0.2732977213},
{"learn":[3.397245411],"iteration":772,"passed_time":0.9270406184,"remaining_time":0.2722357314},
{"learn":[3.396229831],"iteration":773,"passed_time":0.9279395106,"remaining_time":0.270948746},
{"learn":[3.394002836],"iteration":774,"passed_time":0.9290724695,"remaining_time":0.269730717},
{"learn":[3.389617243],"iteration":775,"passed_time":0.9303142672,"remaining_time":0.2685443246},
{"learn":[3.385426488],"iteration":776,"passed_time":0.9316029041,"remaining_time":0.2673712325},
{"learn":[3.385072258],"iteration":777,"passed_time":0.9327574693,"remaining_time":0.2661595864},
{"learn":[3.383842366],"iteration":778,"passed_time":0.939334014,"remaining_time":0.2664862864},
{"learn":[3.380110746],"iteration":779,"passed_time":0.9404649898,"remaining_time":0.2652593561},
{"learn":[3.378595218],"iteration":780,"passed_time":0.9413964985,"remaining_time":0.263976739},
{"learn":[3.377371219],"iteration":781,"passed_time":0.9421180577,"remaining_time":0.2626364918},
{"learn":[3.375814782],"iteration":782,"passed_time":0.9428009789,"remaining_time":0.2612871168},
{"learn":[3.374195887],"iteration":783,"passed_time":0.9434406792,"remaining_time":0.2599275341},
{"learn":[3.373704309],"iteration":784,"passed_time":0.9441300538,"remaining_time":0.2585833905},
{"learn":[3.372971757],"iteration":785,"passed_time":0.9448725764,"remaining_time":0.2572553834},
{"learn":[3.371565136],"iteration":786,"passed_time":0.9457633414,"remaining_time":0.2559689857},
{"learn":[3.3700309],"iteration":787,"passed_time":0.9466553618,"remaining_time":0.2546839298},
{"learn":[3.368186663],"iteration":788,"passed_time":0.9477159301,"remaining_time":0.2534449445},
{"learn":[3.366710398],"iteration":789,"passed_time":0.9536286768,"remaining_time":0.2534962305},
{"learn":[3.364598042],"iteration":790,"passed_time":0.955561186,"remaining_time":0.2524807685},
{"learn":[3.36348442],"iteration":791,"passed_time":0.9569000106,"remaining_time":0.2513070735},
{"learn":[3.362001759],"iteration":792,"passed_time":0.9580735377,"remaining_time":0.2500898137},
{"learn":[3.361580401],"iteration":793,"passed_time":0.9595286856,"remaining_time":0.2489457295},
{"learn":[3.359543675],"iteration":794,"passed_time":0.9606989809,"remaining_time":0.2477274102},
{"learn":[3.35766119],"iteration":795,"passed_time":0.9620656148,"remaining_time":0.2465595294},
{"learn":[3.354592969],"iteration":796,"passed_time":0.9628734747,"remaining_time":0.2452488273},
{"learn":[3.350985986],"iteration":797,"passed_time":0.965325809,"remaining_time":0.2443556559},
{"learn":[3.349589624],"iteration":798,"passed_time":0.9669933921,"remaining_time":0.2432611662},
{"learn":[3.349110856],"iteration":799,"passed_time":0.9680081757,"remaining_time":0.2420020439},
{"learn":[3.345315441],"iteration":800,"passed_time":0.9690061914,"remaining_time":0.2407393659},
{"learn":[3.34397474],"iteration":801,"passed_time":0.9704715816,"remaining_time":0.2395927346},
{"learn":[3.343800902],"iteration":802,"passed_time":0.971789652,"remaining_time":0.2384091674},
{"learn":[3.342329465],"iteration":803,"passed_time":0.9727968394,"remaining_time":0.2371494783},
{"learn":[3.34220347],"iteration":804,"passed_time":0.9734252336,"remaining_time":0.2357986591},
{"learn":[3.341279219],"iteration":805,"passed_time":0.9740503138,"remaining_time":0.2344488348},
{"learn":[3.337329521],"iteration":806,"passed_time":0.9746775492,"remaining_time":0.2331013222},
{"learn":[3.336708453],"iteration":807,"passed_time":0.9756901447,"remaining_time":0.2318471631},
{"learn":[3.333252703],"iteration":808,"passed_time":0.9765780603,"remaining_time":0.230564165},
{"learn":[3.332186769],"iteration":809,"passed_time":0.9776701654,"remaining_time":0.2293300388},
{"learn":[3.330594851],"iteration":810,"passed_time":0.978831194,"remaining_time":0.2281123251},
{"learn":[3.327867442],"iteration":811,"passed_time":0.9806361461,"remaining_time":0.2270438368},
{"learn":[3.327563111],"iteration":812,"passed_time":0.9817806682,"remaining_time":0.2258216297},
{"learn":[3.326308994],"iteration":813,"passed_time":0.9827051337,"remaining_time":0.2245493303},
{"learn":[3.326249879],"iteration":814,"passed_time":0.9834930696,"remaining_time":0.2232468931},
{"learn":[3.322336238],"iteration":815,"passed_time":0.9841476429,"remaining_time":0.221915645},
{"learn":[3.320491154],"iteration":816,"passed_time":0.9847638286,"remaining_time":0.2205774549},
{"learn":[3.320434271],"iteration":817,"passed_time":0.9853433425,"remaining_time":0.2192328708},
{"learn":[3.319609638],"iteration":818,"passed_time":0.9859374816,"remaining_time":0.2178933873},
{"learn":[3.316182682],"iteration":819,"passed_time":0.9865790986,"remaining_time":0.2165661436},
{"learn":[3.313126612],"iteration":820,"passed_time":0.9871759367,"remaining_time":0.2152308071},
{"learn":[3.311222803],"iteration":821,"passed_time":0.9879383892,"remaining_time":0.2139331305},
{"learn":[3.309627335],"iteration":822,"passed_time":0.9892134135,"remaining_time":0.2127469917},
{"learn":[3.307974895],"iteration":823,"passed_time":0.990047208,"remaining_time":0.2114663939},
{"learn":[3.307321505],"iteration":824,"passed_time":0.9906803305,"remaining_time":0.2101443125},
{"learn":[3.306759087],"iteration":825,"passed_time":0.9913194736,"remaining_time":0.2088251676},
{"learn":[3.30484037],"iteration":826,"passed_time":0.9919520382,"remaining_time":0.2075062909},
{"learn":[3.30201994],"iteration":827,"passed_time":0.9926176453,"remaining_time":0.206195936},
{"learn":[3.299302297],"iteration":828,"passed_time":0.9943062296,"remaining_time":0.2050981487},
{"learn":[3.298132671],"iteration":829,"passed_time":0.9954782685,"remaining_time":0.2038931393},
{"learn":[3.296976183],"iteration":830,"passed_time":0.9967208317,"remaining_time":0.2027025518},
{"learn":[3.293144745],"iteration":831,"passed_time":0.9975009202,"remaining_time":0.201418455},
{"learn":[3.290284404],"iteration":832,"passed_time":0.9983126899,"remaining_time":0.2001419198},
{"learn":[3.288285745],"iteration":833,"passed_time":0.9989676733,"remaining_time":0.1988352923},
{"learn":[3.286662667],"iteration":834,"passed_time":0.9996039166,"remaining_time":0.1975265224},
{"learn":[3.285692682],"iteration":835,"passed_time":1.000209328,"remaining_time":0.1962133132},
{"learn":[3.284565611],"iteration":836,"passed_time":1.00084362,"remaining_time":0.1949074195},
{"learn":[3.283897383],"iteration":837,"passed_time":1.001508843,"remaining_time":0.1936091082},
{"learn":[3.280712855],"iteration":838,"passed_time":1.002984591,"remaining_time":0.1924678417},
{"learn":[3.280468341],"iteration":839,"passed_time":1.003792389,"remaining_time":0.1911985502},
{"learn":[3.277814895],"iteration":840,"passed_time":1.004437526,"remaining_time":0.1898996037},
{"learn":[3.276316385],"iteration":841,"passed_time":1.005030221,"remaining_time":0.1885923693},
{"learn":[3.27557063],"iteration":842,"passed_time":1.005653959,"remaining_time":0.1872926116},
{"learn":[3.27499628],"iteration":843,"passed_time":1.006267964,"remaining_time":0.1859926569},
{"learn":[3.273569958],"iteration":844,"passed_time":1.006880033,"remaining_time":0.1846939705},
{"learn":[3.269665595],"iteration":845,"passed_time":1.009105727,"remaining_time":0.1836906406},
{"learn":[3.267984685],"iteration":846,"passed_time":1.010476602,"remaining_time":0.1825300119},
{"learn":[3.267702508],"iteration":847,"passed_time":1.011262831,"remaining_time":0.1812640923},
{"learn":[3.266671924],"iteration":848,"passed_time":1.012065666,"remaining_time":0.1800022563},
{"learn":[3.265359825],"iteration":849,"passed_time":1.013035434,"remaining_time":0.1787709589},
{"learn":[3.2618983],"iteration":850,"passed_time":1.013764151,"remaining_time":0.177498071},
{"learn":[3.260456253],"iteration":851,"passed_time":1.014641943,"remaining_time":0.1762523563},
{"learn":[3.258389147],"iteration":852,"passed_time":1.015442914,"remaining_time":0.1749942653},
{"learn":[3.258108469],"iteration":853,"passed_time":1.01641752,"remaining_time":0.1737669296},
{"learn":[3.256424936],"iteration":854,"passed_time":1.0177483,"remaining_time":0.172600589},
{"learn":[3.254817983],"iteration":855,"passed_time":1.018571371,"remaining_time":0.171348455},
{"learn":[3.253898449],"iteration":856,"passed_time":1.019402739,"remaining_time":0.1700987067},
{"learn":[3.253023652],"iteration":857,"passed_time":1.020242582,"remaining_time":0.1688513364},
{"learn":[3.252845542],"iteration":858,"passed_time":1.02124488,"remaining_time":0.1676315811},
{"learn":[3.252316026],"iteration":859,"passed_time":1.022040033,"remaining_time":0.16637861},
{"learn":[3.24975301],"iteration":860,"passed_time":1.024533355,"remaining_time":0.1654008553},
{"learn":[3.249151075],"iteration":861,"passed_time":1.02580839,"remaining_time":0.164224545},
{"learn":[3.246257135],"iteration":862,"passed_time":1.026830932,"remaining_time":0.1630079232},
{"learn":[3.243826471],"iteration":863,"passed_time":1.027851169,"remaining_time":0.1617913877},
{"learn":[3.243190653],"iteration":864,"passed_time":1.02911933,"remaining_time":0.1606139994},
{"learn":[3.24008797],"iteration":865,"passed_time":1.030345829,"remaining_time":0.1594299551},
{"learn":[3.240036811],"iteration":866,"passed_time":1.031330949,"remaining_time":0.1582087845},
{"learn":[3.238676314],"iteration":867,"passed_time":1.032041542,"remaining_time":0.1569464097},
{"learn":[3.237848782],"iteration":868,"passed_time":1.032798067,"remaining_time":0.1556922288},
{"learn":[3.236405498],"iteration":869,"passed_time":1.033699488,"remaining_time":0.1544608431},
{"learn":[3.233378068],"iteration":870,"passed_time":1.034357757,"remaining_time":0.1531942028},
{"learn":[3.233169169],"iteration":871,"passed_time":1.034968562,"remaining_time":0.1519219908},
{"learn":[3.232434885],"iteration":872,"passed_time":1.035758102,"remaining_time":0.1506772954},
{"learn":[3.229978115],"iteration":873,"passed_time":1.036679503,"remaining_time":0.1494526515},
{"learn":[3.229648848],"iteration":874,"passed_time":1.038576041,"remaining_time":0.1483680058},
{"learn":[3.227208761],"iteration":875,"passed_time":1.040139521,"remaining_time":0.1472343614},
{"learn":[3.226258869],"iteration":876,"passed_time":1.041094975,"remaining_time":0.1460144606},
{"learn":[3.225331995],"iteration":877,"passed_time":1.04193046,"remaining_time":0.1447784921},
{"learn":[3.221968268],"iteration":878,"passed_time":1.042638177,"remaining_time":0.1435258469},
{"learn":[3.221166317],"iteration":879,"passed_time":1.043489656,"remaining_time":0.142294044},
{"learn":[3.220047503],"iteration":880,"passed_time":1.044407902,"remaining_time":0.1410721229},
{"learn":[3.21982781],"iteration":881,"passed_time":1.045351907,"remaining_time":0.1398543368},
{"learn":[3.216693405],"iteration":882,"passed_time":1.046181234,"remaining_time":0.1386219755},
{"learn":[3.214798761],"iteration":883,"passed_time":1.047111669,"remaining_time":0.1374037937},
{"learn":[3.214395085],"iteration":884,"passed_time":1.047820271,"remaining_time":0.1361574363},
{"learn":[3.213470696],"iteration":885,"passed_time":1.048426714,"remaining_time":0.1348991483},
{"learn":[3.211595017],"iteration":886,"passed_time":1.049047266,"remaining_time":0.1336441274},
{"learn":[3.210965255],"iteration":887,"passed_time":1.049741756,"remaining_time":0.1323998611},
{"learn":[3.209413583],"iteration":888,"passed_time":1.050707851,"remaining_time":0.1311907441},
{"learn":[3.208331683],"iteration":889,"passed_time":1.053688488,"remaining_time":0.1302311614},
{"learn":[3.207110711],"iteration":890,"passed_time":1.055507249,"remaining_time":0.1291249048},
{"learn":[3.204519413],"iteration":891,"passed_time":1.058371044,"remaining_time":0.1281435793},
{"learn":[3.201421296],"iteration":892,"passed_time":1.059984429,"remaining_time":0.1270082126},
{"learn":[3.200691259],"iteration":893,"passed_time":1.061529796,"remaining_time":0.1258637119},
{"learn":[3.200485067],"iteration":894,"passed_time":1.062344818,"remaining_time":0.1246326323},
{"learn":[3.197467568],"iteration":895,"passed_time":1.063255097,"remaining_time":0.123413538},
{"learn":[3.195838544],"iteration":896,"passed_time":1.064206036,"remaining_time":0.1221998012},
{"learn":[3.195671746],"iteration":897,"passed_time":1.064997868,"remaining_time":0.1209685774},
{"learn":[3.194213094],"iteration":898,"passed_time":1.065754165,"remaining_time":0.1197343389},
{"learn":[3.192884691],"iteration":899,"passed_time":1.068973853,"remaining_time":0.1187748725},
{"learn":[3.188364239],"iteration":900,"passed_time":1.07162281,"remaining_time":0.1177476783},
{"learn":[3.185219478],"iteration":901,"passed_time":1.072988096,"remaining_time":0.1165774206},
{"learn":[3.184120387],"iteration":902,"passed_time":1.073918944,"remaining_time":0.1153600638},
{"learn":[3.183725321],"iteration":903,"passed_time":1.074699777,"remaining_time":0.11412741},
{"learn":[3.181264554],"iteration":904,"passed_time":1.075816715,"remaining_time":0.1129310364},
{"learn":[3.180741589],"iteration":905,"passed_time":1.077846011,"remaining_time":0.1118294978},
{"learn":[3.179782639],"iteration":906,"passed_time":1.078878909,"remaining_time":0.110623747},
{"learn":[3.176377564],"iteration":907,"passed_time":1.079711978,"remaining_time":0.1093981299},
{"learn":[3.174078182],"iteration":908,"passed_time":1.080506559,"remaining_time":0.1081695235},
{"learn":[3.171242379],"iteration":909,"passed_time":1.082342741,"remaining_time":0.1070448865},
{"learn":[3.170421012],"iteration":910,"passed_time":1.084679637,"remaining_time":0.1059676045},
{"learn":[3.170087224],"iteration":911,"passed_time":1.085805717,"remaining_time":0.1047707271},
{"learn":[3.167303059],"iteration":912,"passed_time":1.086803131,"remaining_time":0.1035617441},
{"learn":[3.16705966],"iteration":913,"passed_time":1.087622457,"remaining_time":0.1023364675},
{"learn":[3.165667683],"iteration":914,"passed_time":1.088370609,"remaining_time":0.1011054664},
{"learn":[3.164689733],"iteration":915,"passed_time":1.088984549,"remaining_time":0.09986321191},
{"learn":[3.163311455],"iteration":916,"passed_time":1.089601358,"remaining_time":0.09862258748},
{"learn":[3.159425016],"iteration":917,"passed_time":1.090227057,"remaining_time":0.09738411625},
{"learn":[3.159327058],"iteration":918,"passed_time":1.090799346,"remaining_time":0.09614227096},
{"learn":[3.15819426],"iteration":919,"passed_time":1.091393714,"remaining_time":0.09490380117},
{"learn":[3.157086603],"iteration":920,"passed_time":1.091993625,"remaining_time":0.09366720565},
{"learn":[3.153354154],"iteration":921,"passed_time":1.092616165,"remaining_time":0.09243390553},
{"learn":[3.153261317],"iteration":922,"passed_time":1.093207865,"remaining_time":0.09119935603},
{"learn":[3.153168454],"iteration":923,"passed_time":1.093877646,"remaining_time":0.08997262023},
{"learn":[3.152080399],"iteration":924,"passed_time":1.094720076,"remaining_time":0.08876108724},
{"learn":[3.151635144],"iteration":925,"passed_time":1.09689702,"remaining_time":0.08765699729},
{"learn":[3.147762655],"iteration":926,"passed_time":1.097827803,"remaining_time":0.08645245913},
{"learn":[3.147172317],"iteration":927,"passed_time":1.098928737,"remaining_time":0.08526171234},
{"learn":[3.146254125],"iteration":928,"passed_time":1.09982773,"remaining_time":0.08405572532},
{"learn":[3.144869828],"iteration":929,"passed_time":1.100653107,"remaining_time":0.08284485753},
{"learn":[3.143466218],"iteration":930,"passed_time":1.101534654,"remaining_time":0.08163898082},
{"learn":[3.141919643],"iteration":931,"passed_time":1.10222117,"remaining_time":0.08041957036},
{"learn":[3.141054135],"iteration":932,"passed_time":1.102943757,"remaining_time":0.07920389252},
{"learn":[3.139390417],"iteration":933,"passed_time":1.103613388,"remaining_time":0.07798552851},
{"learn":[3.139025283],"iteration":934,"passed_time":1.104576507,"remaining_time":0.07678874112},
{"learn":[3.137824183],"iteration":935,"passed_time":1.105393004,"remaining_time":0.07558242763},
{"learn":[3.135620453],"iteration":936,"passed_time":1.106066649,"remaining_time":0.07436734137},
{"learn":[3.13443178],"iteration":937,"passed_time":1.106705163,"remaining_time":0.07315108755},
{"learn":[3.132765713],"iteration":938,"passed_time":1.108798295,"remaining_time":0.07203056014},
{"learn":[3.131434124],"iteration":939,"passed_time":1.11052543,"remaining_time":0.07088460189},
{"learn":[3.128384262],"iteration":940,"passed_time":1.111743123,"remaining_time":0.06970546679},
{"learn":[3.128120455],"iteration":941,"passed_time":1.112537272,"remaining_time":0.06850017173},
{"learn":[3.126314615],"iteration":942,"passed_time":1.113198027,"remaining_time":0.06728768563},
{"learn":[3.125409666],"iteration":943,"passed_time":1.113806971,"remaining_time":0.06607329491},
{"learn":[3.123072589],"iteration":944,"passed_time":1.114436996,"remaining_time":0.06486141249},
{"learn":[3.122921099],"iteration":945,"passed_time":1.115157441,"remaining_time":0.06365592156},
{"learn":[3.122182662],"iteration":946,"passed_time":1.115899379,"remaining_time":0.06245265797},
{"learn":[3.120040951],"iteration":947,"passed_time":1.116831616,"remaining_time":0.06126080593},
{"learn":[3.118767799],"iteration":948,"passed_time":1.117798701,"remaining_time":0.06007137379},
{"learn":[3.118203218],"iteration":949,"passed_time":1.11850796,"remaining_time":0.05886884002},
{"learn":[3.116343362],"iteration":950,"passed_time":1.11918549,"remaining_time":0.05766570871},
{"learn":[3.11480829],"iteration":951,"passed_time":1.119996524,"remaining_time":0.05647041298},
{"learn":[3.112607903],"iteration":952,"passed_time":1.120963242,"remaining_time":0.05528360168},
{"learn":[3.111661241],"iteration":953,"passed_time":1.121996856,"remaining_time":0.05410047734},
{"learn":[3.110249676],"iteration":954,"passed_time":1.124386538,"remaining_time":0.05298156461},
{"learn":[3.107333579],"iteration":955,"passed_time":1.125332438,"remaining_time":0.05179354318},
{"learn":[3.107149851],"iteration":956,"passed_time":1.126029072,"remaining_time":0.05059482768},
{"learn":[3.106867336],"iteration":957,"passed_time":1.126808884,"remaining_time":0.04940080702},
{"learn":[3.10364681],"iteration":958,"passed_time":1.127574293,"remaining_time":0.04820703441},
{"learn":[3.102703811],"iteration":959,"passed_time":1.128303009,"remaining_time":0.04701262539},
{"learn":[3.101469264],"iteration":960,"passed_time":1.12913625,"remaining_time":0.04582342742},
{"learn":[3.09863569],"iteration":961,"passed_time":1.129980563,"remaining_time":0.04463540687},
{"learn":[3.09645939],"iteration":962,"passed_time":1.130827491,"remaining_time":0.04344820061},
{"learn":[3.096240186],"iteration":963,"passed_time":1.131567644,"remaining_time":0.04225771283},
{"learn":[3.094838828],"iteration":964,"passed_time":1.13221549,"remaining_time":0.04106481054},
{"learn":[3.094176802],"iteration":965,"passed_time":1.132879172,"remaining_time":0.03987359403},
{"learn":[3.093182279],"iteration":966,"passed_time":1.133567709,"remaining_time":0.03868431686},
{"learn":[3.090150687],"iteration":967,"passed_time":1.134229515,"remaining_time":0.03749519058},
{"learn":[3.088612829],"iteration":968,"passed_time":1.134971719,"remaining_time":0.03630972476},
{"learn":[3.087153684],"iteration":969,"passed_time":1.135660889,"remaining_time":0.03512353264},
{"learn":[3.085866843],"iteration":970,"passed_time":1.136930847,"remaining_time":0.03395571015},
{"learn":[3.082669094],"iteration":971,"passed_time":1.138547437,"remaining_time":0.0327976628},
{"learn":[3.081047548],"iteration":972,"passed_time":1.139564606,"remaining_time":0.03162203944},
{"learn":[3.079684322],"iteration":973,"passed_time":1.140490361,"remaining_time":0.03044430122},
{"learn":[3.07613431],"iteration":974,"passed_time":1.141563698,"remaining_time":0.02927086406},
{"learn":[3.074005935],"iteration":975,"passed_time":1.142384302,"remaining_time":0.02809141726},
{"learn":[3.072988853],"iteration":976,"passed_time":1.14362705,"remaining_time":0.02692264294},
{"learn":[3.072344268],"iteration":977,"passed_time":1.144338016,"remaining_time":0.02574175497},
{"learn":[3.070654438],"iteration":978,"passed_time":1.144992344,"remaining_time":0.02456061207},
{"learn":[3.069724506],"iteration":979,"passed_time":1.145591134,"remaining_time":0.02337941089},
{"learn":[3.067763166],"iteration":980,"passed_time":1.146215692,"remaining_time":0.02219989617},
{"learn":[3.066737893],"iteration":981,"passed_time":1.146912424,"remaining_time":0.02102283466},
{"learn":[3.065248174],"iteration":982,"passed_time":1.147584397,"remaining_time":0.01984632223},
{"learn":[3.063186837],"iteration":983,"passed_time":1.14818359,"remaining_time":0.01866965187},
{"learn":[3.062880371],"iteration":984,"passed_time":1.148784535,"remaining_time":0.01749418074},
{"learn":[3.061288645],"iteration":985,"passed_time":1.149407892,"remaining_time":0.01632019319},
{"learn":[3.059970575],"iteration":986,"passed_time":1.150760791,"remaining_time":0.01515693038},
{"learn":[3.059576341],"iteration":987,"passed_time":1.154191872,"remaining_time":0.01401852476},
{"learn":[3.058175919],"iteration":988,"passed_time":1.155191779,"remaining_time":0.01284844244},
{"learn":[3.056830702],"iteration":989,"passed_time":1.156536775,"remaining_time":0.01168218965},
{"learn":[3.056336579],"iteration":990,"passed_time":1.157346007,"remaining_time":0.01051071046},
{"learn":[3.055810414],"iteration":991,"passed_time":1.158427592,"remaining_time":0.009342158004},
{"learn":[3.055476518],"iteration":992,"passed_time":1.159516667,"remaining_time":0.008173833506},
{"learn":[3.053331734],"iteration":993,"passed_time":1.16059613,"remaining_time":0.007005610445},
{"learn":[3.050890374],"iteration":994,"passed_time":1.161487195,"remaining_time":0.005836619072},
{"learn":[3.04972623],"iteration":995,"passed_time":1.162367213,"remaining_time":0.004668141418},
{"learn":[3.047217327],"iteration":996,"passed_time":1.163232615,"remaining_time":0.00350019844},
{"learn":[3.047155483],"iteration":997,"passed_time":1.164134583,"remaining_time":0.002332935035},
{"learn":[3.04430671],"iteration":998,"passed_time":1.168230426,"remaining_time":0.001169399826},
{"learn":[3.042664195],"iteration":999,"passed_time":1.170014359,"remaining_time":0}
]}